Workbook

Sheet Cover
B15: Prepared By
B16: Analyst | C16: Raman Singh
B17: Company | C17: Reliance Industries Ltd.
B18: Currency | C18: INR (₹)
B19: Report Date | C19: 46247
B21: Valuation Framework
B22: Methodology | C22: Description
B23: Primary Valuation | C23: Sum-of-the-parts (SOTP) Valuation
B24: Secondary Valuation | C24: Discounted Cash Flow (DCF)
B25: Supporting Analysis | C25: Segment-wise DCF Analysis
B26: Market Benchmarking | C26: Relative Valuation (EV/EBITDA, P/E)
B27: Risk Assessment | C27: Sensitivity & Scenario Analysis
B29: Analysis Period
B30: Period | C30: Timeline
B31: Historical Financials | C31: FY2021-22 to FY2025-26
B32: Forecast Period | C32: FY2026-27E to FY2030-31E
B34: Valuation Summary
B35: Valuation Metric | C35: Output Cell
B36: SOTP Intrinsic Target Price | C36: ='13_Executive_Summary'!B7 -> 1397.149
B37: DCF Intrinsic Target Price | C37: ='13_Executive_Summary'!B8 -> 1344.9807
B38: Current NSE Market Price (As of Aug 12, 2026) | C38: ='13_Executive_Summary'!B9 -> 1310
B39: Weighted Target Price (SOTP:0.8, DCF:0.2) | C39: ='13_Executive_Summary'!B10 -> 1386.7154
B40: RECOMMENDATION | C40: =IF((C39/C38-1)>25%,"STRONG BUY", IF((C39/C38-1)>15%,"BUY", IF((C39/C38-1)>0%,"HOLD","SELL"))) -> HOLD

Sheet 01_Overview
B2: MODEL OVERVIEW & KEY ASSUMPTIONS
B4: Valuation Approach | C4: Blended Sum-of-the-Parts (SOTP) & Discounted Cash Flow (DCF)
B6: Forecast Period | C6: FY 2026-27 to FY 2030-31
B7: Terminal Growth Rate | C7: ='07_Forecast_assumptions'!C11/100 -> 0.05
B9: Key Assumptions
B10: Risk Free Rate | C10: 0.0684 | D10: 10 Year GOI Bond Yield
B11: Equity Risk Premium | C11: 0.075 | D11: Market risk premium for India
B12: Tax Rate | C12: 0.2517 | D12: Effective Tax Rate
B13: Terminal Value Methodology | C13: Gordon Growth
B14: Shares Outstanding | C14: 1,353.25 Cr

Sheet 02_Consolidated_Historical_Data
A1: RELIANCE INDUSTRIES LIMITED
A2: PROFIT & LOSS STATEMENT (CONSOLIDATED)
A3: (₹ in Crore)
A5: Consolidated Line Item | B5: FY 2021-22 | C5: FY 2022-23 | D5: FY 2023-24 | E5: FY 2024-25 | F5: FY 2025-26
A6: Revenue (Value of Sales & Services) | B6: 788743 | C6: 974864 | D6: 1000122 | E6: 1071174 | F6: 1175919
A7: Revenue from Operations | B7: 699934 | C7: 877035 | D7: 914472 | E7: 980136 | F7: 1075675
A8: Other Income | B8: 14947 | C8: 11713 | D8: 16057 | E8: 17978 | F8: 19252
A9: Total Income | B9: 732578 | C9: 903045 | D9: 930529 | E9: 998114 | F9: 1104637
A11: Raw Material Cost | B11: 374210 | C11: 491230 | D11: 468905 | E11: 498220 | F11: 542110
A12: Purchase of Stock-in-Trade | B12: 102450 | C12: 142105 | D12: 175600 | E12: 192440 | F12: 212305
A13: Employee Benefit Expense | B13: 18775 | C13: 22234 | D13: 25690 | E13: 28559 | F13: 30318
A14: Other Operating Expenses | B14: 80815 | C14: 67546 | D14: 65987 | E14: 77495 | F14: 82031
A16: EBITDA | B16: 123684 | C16: 153920 | D16: 178290 | E16: 183422 | F16: 207911
A17: Depreciation & Amortisation | B17: 29782 | C17: 40303 | D17: 50832 | E17: 53136 | F17: 57688
A19: Financial Cost | B19: 14584 | C19: 19571 | D19: 23118 | E19: 24269 | F19: 27061
A20: Profit Before Tax (PBT) | B20: 88437 | C20: 105759 | D20: 120784 | E20: 123995 | F20: 142414
... A29: Diluted EPS (₹) | B29: 89.5 | C29: 98 | D29: 102.9 | E29: 51.5 | F29: 59.7
A49: KPIs
A50: Revenue % automotive y-o-y
A51: Revenue % generation y-o-y
A52: Revenue % services y-o-y
A53: GP% automotive
A54: GP% energy generation and automotive
A55: GP% services and other
A56: Overall GP%
A57: EBIT %
A58: Net loss %
A59: ROA
A60: ROE

Sheet 03_Consolidated_Balance_Sheet_
A1: RELIANCE INDUSTRIES LIMITED
A2: BALANCE SHEET (CONSOLIDATED)
A3: (₹ in Crore)
A5: Consolidated Line Item | B5: FY 2021-22 | C5: FY 2022-23 | D5: FY 2023-24 | E5: FY 2024-25 | F5: FY 2025-26 | I5: Consolidated Line Item | J5: FY 2021-22 | K5: FY 2022-23 | L5: FY 2023-24 | M5: FY 2024-25 | N5: FY 2025-26
A6: ASSETS | I6: EQUITIES AND LIABILITIES
A7: NON-CURRENT ASSETS | I7: EQUITY
A8: Property, Plant & Equipment ₹ Crore | B8: 532042 | C8: 570503 | D8: 606084 | E8: 683102 | F8: 751087 | I8: Equity Share Capital ₹ Crore | J8: 6765 | K8: 6766 | L8: 6766 | M8: 13532 | N8: 13532
A9: Capital Work-in-Progress ₹ Crore | B9: 165410 | C9: 117259 | D9: 152382 | E9: 169710 | F9: 192287 | I9: Other Equity ₹ Crore | J9: 638362 | K9: 662114 | L9: 781537 | M9: 829668 | N9: 890498
A10: Spectrum & Related Assets ₹ Crore | B10: 122313 | C10: 197708 | D10: 199454 | E10: 201298 | F10: 196731 | I10: Non-Controlling Interest ₹ Crore | J10: 109110 | K10: 119104 | L10: 132307 | M10: 166426 | N10: 181836
A11: Goodwill & Intangible Assets ₹ Crore | B11: 89421 | C11: 133087 | D11: 160920 | E11: 207641 | F11: 222376 | I11: TOTAL EQUITY ₹ Crore | J11: 754237 | K11: 787984 | L11: 920610 | M11: 1009626 | N11: 1085866
A12: Non-Current Investments ₹ Crore | B12: 110432 | C12: 117087 | D12: 119502 | E12: 123672 | F12: 150901
A13: Loans & Other Financial Assets ₹ Crore | B13: 3926 | C13: 4048 | D13: 3521 | E13: 6830 | F13: 5725 | I13: NON-CURRENT LIABILITIES
A14: Deferred Tax Assets (Net) ₹ Crore | B14: 1215 | C14: 1549 | D14: 938 | E14: 408 | F14: 594 | I14: Long-Term Borrowings ₹ Crore | J14: 180410 | K14: 224195 | L14: 224195 | M14: 236899 | N14: 270751
A15: Other Non-Current Assets ₹ Crore | B15: 35420 | C15: 40894 | D15: 43085 | E15: 58190 | F15: 64190 | I15: Lease Liabilities ₹ Crore | J15: 14205 | K15: 14584 | L15: 16057 | M15: 17142 | N15: 16198
A16: TOTAL NON-CURRENT ASSETS ₹ Crore | B16: 960179 | C16: 1182135 | D16: 1285886 | E16: 1450851 | F16: 1583891 | I16: Deferred Payment Liabilities ₹ Crore | J16: 78590 | K16: 80815 | L16: 91400 | M16: 104410 | N16: 99552
I17: Deferred Tax Liabilities (Net) ₹ Crore | J17: 48200 | K17: 49000 | L17: 50832 | M17: 83453 | N17: 97961
A18: CURRENT ASSETS | I18: Other Non-Current Liabilities ₹ Crore | J18: 28733 | K18: 30403 | L18: 29173 | M18: 44854 | N18: 66558
A19: Inventories ₹ Crore | B19: 107741 | C19: 141114 | D19: 144271 | E19: 146062 | F19: 166941 | I19: TOTAL NON-CURRENT LIABILITIES ₹ Crore | J19: 350138 | K19: 398997 | L19: 421657 | M19: 486758 | N19: 551020
A20: Current Investments ₹ Crore | B20: 141107 | C20: 112390 | D20: 118709 | E20: 118709 | F20: 97431
A21: Trade Receivables ₹ Crore | B21: 18775 | C21: 19811 | D21: 21410 | E21: 42121 | F21: 58491 | I21: CURRENT LIABILITIES
A22: Cash & Cash Equivalents ₹ Crore | B22: 36178 | C22: 6851 | D22: 10211 | E22: 106502 | F22: 145977 | I22: Short-Term Borrowings ₹ Crore | J22: 44213 | K22: 48200 | L22: 103670 | M22: 110631 | N22: 103670
A23: Current Loans & Financial Assets ₹ Crore | B23: 23715 | C23: 22542 | D23: 29560 | E23: 28728 | F23: 62796 | I23: Current Lease Liabilities ₹ Crore | J23: 4114 | K23: 4147 | L23: 4903 | M23: 4903 | N23: 7381
A24: Other Current Assets ₹ Crore | B24: 27249 | C24: 31500 | D24: 36000 | E24: 57148 | F24: 62613 | I24: Trade Payables ₹ Crore | J24: 102450 | K24: 142105 | L24: 132912 | M24: 186789 | N24: 158842
A25: TOTAL CURRENT ASSETS ₹ Crore | B25: 354765 | C25: 334208 | D25: 360161 | E25: 499270 | F25: 594249 | I25: Other Current Financial Liabilities ₹ Crore | J25: 22434 | K25: 27170 | L25: 25690 | M25: 57143 | N25: 64660
I26: Other Current Liabilities ₹ Crore | J26: 32856 | K26: 103670 | L26: 31500 | M26: 90124 | N26: 201503
A27: TOTAL ASSETS ₹ Crore | B27: =SUM(B16+B25) -> 1314944 | C27: =SUM(C16+C25) -> 1516343 | D27: =SUM(D16+D25) -> 1646047 | E27: =SUM(E16+E25) -> 1950121 | F27: =SUM(F16+F25) -> 2178140 | I27: Current Provisions ₹ Crore | J27: 4502 | K27: 4070 | L27: 5105 | M27: 4147 | N27: 5198
I28: TOTAL CURRENT LIABILITIES ₹ Crore | J28: 210569 | K28: 329362 | L28: 303780 | M28: 453737 | N28: 541254
I30: TOTAL LIABILITIES ₹ Crore | J30: 560707 | K30: 728359 | L30: 725437 | M30: 940495 | N30: 1092274
I32: TOTAL EQUITY AND LIABILITIES ₹ Crore | J32: 1314944 | K32: 1516343 | L32: 1646047 | M32: 1950121 | N32: 2178140

Sheet 04_Consolidated_Cash_Flow
A1: RELIANCE INDUSTRIES LIMITED
A2: CASH FLOW (CONSOLIDATED)
A3: (₹ in Crore)
A5: Particular Units | B5: FY 2021-22 | C5: FY 2022-23 | D5: FY 2023-24 | E5: FY 2024-25 | F5: FY 2025-26
A6: Operating Cash Flow (CFO) ₹ Crore (A) | B6: 110654 | C6: 115020 | D6: 158788 | E6: 178703 | F6: 192113
A8: Capital Expenditure (CAPEX) ₹ Crore {PPE + Spectrum + Intangibles} | B8: -109162 | C8: -93001 | D8: -152883 | E8: -139967 | F8: -122916
A9: Other Investing Activities | B9: =B8-B10 -> 941 | C9: =C8-C10 -> -1766 | D9: =D8-D10 -> -38582 | E9: =E8-E10 -> -2432 | F9: =F8-F10 -> -21827
A10: Net Invested Cash Flow - (B) | B10: =-110103 -> -110103 | C10: -91235 | D10: -114301 | E10: -137535 | F10: -101089
A12: Debt Raised / (Repaid) ₹ Crore | B12: 22372 | C12: 16544 | D12: -9880 | E12: -24448 | F12: -44106
A13: Dividends Paid ₹ Crore | B13: -5083 | C13: -6089 | D13: -6766 | E13: -7443 | F13: -7443
A15: Financing Cash Flow (Calculated) ₹ Crore - (C) | B15: =SUM(B12:B13) -> 17289 | C15: =SUM(C12:C13) -> 10455 | D15: =SUM(D12:D13) -> -16646 | E15: =SUM(E12:E13) -> -31891 | F15: =SUM(F12:F13) -> -51549
A17: Net Increase in Cash & Cash Equiv. (A+B+C) | B17: =SUM(B6,B10,B15) -> 17840 | C17: =SUM(C6,C10,C15) -> 34240 | D17: =SUM(D6,D10,D15) -> 27841 | E17: =SUM(E6,E10,E15) -> 9277 | F17: =SUM(F6,F10,F15) -> 39475
A18: (+) Opening Balance of Cash & Cash Equiv. ₹ Crore | B18: 18338 | C18: 34412 | D18: 69384 | E18: 97225 | F18: 106502
A20: (=) Closing Balance of Cash & Cash Equiv. ₹ Crore | B20: =SUM(B17:B18) -> 36178 | C20: =SUM(C17:C18) -> 68652 | D20: =SUM(D17:D18) -> 97225 | E20: =SUM(E17:E18) -> 106502 | F20: =SUM(F17:F18) -> 145977

Sheet 05_Segment_Historical_Raw_Data
A1: RELIANCE INDUSTRIES LIMITED
A2: PROFIT & LOSS STATEMENT (SEGMENT WISE)
A3: (₹ in Crore)
A5: Line Item | B5: FY 2021-22 | C5: FY 2022-23 | D5: FY 2023-24 | E5: FY 2024-25 | F5: FY 2025-26
A6: Oil-to-Chemical (O2C) Segment
A7: Revenue (Value of Sales & Services) | B7: 584298 | C7: 631425 | D7: 564749 | E7: 626921 | F7: 662401
A8: Revenue Growth % | B8: - | C8: =C7/B7-1 -> 0.080655761 | D8: =D7/C7-1 -> -0.10559607 | E8: =E7/D7-1 -> 0.11008784 | F8: =F7/E7-1 -> 0.056594053
A9: EBITDA | B9: 76701 | C9: 62128 | D9: 62389 | E9: 54988 | F9: 60546
A10: EBITDA Margin % | B10: =B9/B7 -> 0.13127034 | C10: =C9/C7 -> 0.098393317 | D10: =D9/D7 -> 0.11047209 | E10: =E9/E7 -> 0.087711211 | F10: =F9/F7 -> 0.091403848
A11: Segment Result (EBIT) - Reported | B11: 63705 | C11: 52620 | D11: 53613 | E11: 47257 | F11: 50758
A12: EBIT Margin % | B12: =B11/B7 -> 0.10902827 | C12: =C11/C7 -> 0.083335313 | D12: =D11/D7 -> 0.094932439 | E12: =E11/E7 -> 0.075379514 | F12: =F11/F7 -> 0.0766273
A13: Capital Expenditure | B13: 20732 | C13: 19511 | D13: 21589 | E13: 26573 | F13: 32365
A14: Depreciation - Reported | B14: 6951 | C14: 7508 | D14: 7297 | E14: 7731 | F14: 9788
A15: Production Meant for Sale MMT | B15: 71.5 | C15: 71.4 | D15: 71.6 | E15: 71.2 | F15: 70.9
A16: Refinery Throughput MMT | B16: 70.3 | C16: 78.2 | D16: 78.2 | E16: 79.4 | F16: 80
A17: Gross Refining Margin (GRM) $/bbl | B17: 9.4 | C17: 10 | D17: 12.8 | E17: 10.7 | F17: 11
A18: Refining Utilisation % | B18: 1.01 | C18: 1.05 | D18: 1.05 | E18: 1.06 | F18: 1.07
A20: Digital Services
A21: Revenue (Value of Sales & Services) | B21: 94547 | C21: 115099 | D21: 132938 | E21: 154119 | F21: 176164
A22: Revenue from Operations | B22: 81634 | C22: 99842 | D22: 113176 | E22: 131336 | F22: 149965
A23: Revenue Growth % | B23: - | C23: =C22/B22-1 -> 0.22304432 | D23: =D22/C22-1 -> 0.13355101 | E23: =E22/D22-1 -> 0.16045805 | F23: =F22/E22-1 -> 0.1418423
A24: EBITDA | B24: 39526 | C24: 49122 | D24: 56675 | E24: 65001 | F24: 76560
A25: EBITDA Margin % | B25: 0.484 | C25: 0.492 | D25: 0.501 | E25: 0.495 | F25: 0.511
A26: Segment EBIT | B26: 25321 | C26: 30172 | D26: 34572 | E26: 40379 | F26: 49311
A27: EBIT Margin % | B27: 0.31 | C27: 0.302 | D27: 0.305 | E27: 0.307 | F27: 0.329
A28: Capital Expenditure | B28: 29100 | C28: 49000 | D28: 44413 | E28: 36000 | F28: 31500
A29: Depreciation - Reported | B29: 14205 | C29: 18950 | D29: 22103 | E29: 24622 | F29: 27249
A30: Subscriber Base (Million) | B30: 410.2 | C30: 439.3 | D30: 481.8 | E30: 488.2 | F30: 524.4
A31: ARPU /month | B31: 167.6 | C31: 178.2 | D31: 181.7 | E31: 206.2 | F31: 214
A32: Data Traffic Bn GB | B32: 91.4 | C32: 113.3 | D32: 148.5 | E32: 184.5 | F32: 241.4
A34: Reliance Retail
A35: Revenue (Value of Sales & Services) | B35: 199704 | C35: 260364 | D35: 306786 | E35: 330943 | F35: 371085
A36: Revenue from Operations | B36: 174980 | C36: 230931 | D36: 273079 | E36: 291043 | F36: 328202
A37: EBITDA | B37: 12381 | C37: 17928 | D37: 23040 | E37: 25094 | F37: 27034
A38: EBITDA Margin % | B38: =B37/B36 -> 0.070756658 | C38: =C37/C36 -> 0.077633579 | D38: =D37/D36 -> 0.084371189 | E38: =E37/E36 -> 0.086220936 | F38: =F37/F36 -> 0.082370004
A39: Segment EBIT | B39: 9512 | C39: 13425 | D39: 17351 | E39: 18349 | F39: 19166
A40: EBIT Margin % | B40: =B39/B36 -> 0.054360498 | C40: =C39/C36 -> 0.058134248 | D40: =D39/D36 -> 0.06353839 | E40: =E39/E36 -> 0.063045667 | F40: =F39/F36 -> 0.058396963
A41: Capital Expenditure | B41: 10500 | C41: 17400 | D41: 26100 | E41: 19500 | F41: 16200
A42: Depreciation - Reported | B42: 2869 | C42: 4503 | D42: 5689 | E42: 6745 | F42: 7868
A43: Registered Customer Base in Mn | B43: 193 | C43: 249 | D43: 304 | E43: 349 | F43: 387
A44: Total Operational Stores | B44: 15196 | C44: 18040 | D44: 18836 | E44: 18918 | F44: 20160
A45: Annual Footfalls in Mn | B45: 572 | C45: 780 | D45: 943 | E45: 1110 | F45: 1320
A47: Oil & Gas
A48: Revenue (Value of Sales & Services) | B48: 7458 | C48: 16508 | D48: 24278 | E48: 25211 | F48: 23861
A49: EBITDA | B49: 5457 | C49: 13589 | D49: 19657 | E49: 21188 | F49: 19050
A50: EBITDA Margin % | B50: =B49/B48 -> 0.73169751 | C50: =C49/C48 -> 0.82317664 | D50: =D49/D48 -> 0.80966307 | E50: =E49/E48 -> 0.8404268 | F50: =F49/F48 -> 0.79837392
A51: Segment EBIT | B51: 3124 | C51: 9652 | D51: 14640 | E51: 15413 | F51: 12680
A52: Capital Expenditure | B52: 2600 | C52: 4100 | D52: 5400 | E52: 6300 | F52: 5800
A53: Depreciation - Reported | B53: 2333 | C53: 3937 | D53: 5017 | E53: 5775 | F53: 6370
A54: KG-D6 Gas Production (MMSCMD) | B54: 18 | C54: 20 | D54: 28.5 | E54: 29.5 | F54: 25.9
A55: KG-D6 Gas Price Realised ($/mmbtu) | B55: 4.92 | C55: 8.74 | D55: 9.53 | E55: 9.65 | F55: 9.81
A56: CBM Gas Price Realised ($/mmbtu) | B56: 7.13 | C56: 12.35 | D56: 11.6 | E56: 10.95 | F56: 9.43

Sheet 06_Calculated_Ratios
A1: RELIANCE INDUSTRIES LIMITED
A2: CALCULATED RATIOS (CONSOLIDATED & SEGMENT WISE )
A4: Growth Analysis (₹ Crore) | B4: FY 2021-22 | C4: FY 2022-23 | D4: FY 2023-24 | E4: FY 2024-25 | F4: FY 2025-26
A5: Revenue Growth % | B5: NM | C5: ='02_Consolidated_Historical_Data'!C7/'02_Consolidated_Historical_Data'!B7-1 -> 0.25302529 | D5: ='02_Consolidated_Historical_Data'!D7/'02_Consolidated_Historical_Data'!C7-1 -> 0.042685868 | E5: ='02_Consolidated_Historical_Data'!E7/'02_Consolidated_Historical_Data'!D7-1 -> 0.07180537 | F5: ='02_Consolidated_Historical_Data'!F7/'02_Consolidated_Historical_Data'!E7-1 -> 0.097475248
A6: EBITDA Growth % | B6: NM | C6: ='02_Consolidated_Historical_Data'!C16/'02_Consolidated_Historical_Data'!B16-1 -> 0.24446169 | D6: ='02_Consolidated_Historical_Data'!D16/'02_Consolidated_Historical_Data'!C16-1 -> 0.158329 | E6: ='02_Consolidated_Historical_Data'!E16/'02_Consolidated_Historical_Data'!D16-1 -> 0.028784564 | F6: ='02_Consolidated_Historical_Data'!F16/'02_Consolidated_Historical_Data'!E16-1 -> 0.13351179
A7: PAT Growth % | B7: NM | C7: ='02_Consolidated_Historical_Data'!C26/'02_Consolidated_Historical_Data'!B26-1 -> 0.11310891 | D7: ='02_Consolidated_Historical_Data'!D26/'02_Consolidated_Historical_Data'!C26-1 -> 0.072621148 | E7: ='02_Consolidated_Historical_Data'!E26/'02_Consolidated_Historical_Data'!D26-1 -> 0.02896735 | F7: ='02_Consolidated_Historical_Data'!F26/'02_Consolidated_Historical_Data'!E26-1 -> 0.17765561
A8: EPS Growth % | B8: NM | C8: ='02_Consolidated_Historical_Data'!C28/'02_Consolidated_Historical_Data'!B28-1 -> 0.094972067 | D8: ='02_Consolidated_Historical_Data'!D28/'02_Consolidated_Historical_Data'!C28-1 -> 0.05 | E8: ='02_Consolidated_Historical_Data'!E28/'02_Consolidated_Historical_Data'!D28-1 -> -0.49951409 | F8: ='02_Consolidated_Historical_Data'!F28/'02_Consolidated_Historical_Data'!E28-1 -> 0.1592233
A9: EBIT | B9: ='02_Consolidated_Historical_Data'!B16-'02_Consolidated_Historical_Data'!B17 -> 93902 | C9: ='02_Consolidated_Historical_Data'!C16-'02_Consolidated_Historical_Data'!C17 -> 113617 | D9: ='02_Consolidated_Historical_Data'!D16-'02_Consolidated_Historical_Data'!D17 -> 127458 | E9: ='02_Consolidated_Historical_Data'!E16-'02_Consolidated_Historical_Data'!E17 -> 130286 | F9: ='02_Consolidated_Historical_Data'!F16-'02_Consolidated_Historical_Data'!F17 -> 150223
A11: Profitability Margins | B11: FY 2021-22 | C11: FY 2022-23 | D11: FY 2023-24 | E11: FY 2024-25 | F11: FY 2025-26
A12: EBITDA Margin % | B12: ='02_Consolidated_Historical_Data'!B16/'02_Consolidated_Historical_Data'!B7 -> 0.17670809 | C12: ='02_Consolidated_Historical_Data'!C16/'02_Consolidated_Historical_Data'!C7 -> 0.17550041 | D12: ='02_Consolidated_Historical_Data'!D16/'02_Consolidated_Historical_Data'!D7 -> 0.19496496 | E12: ='02_Consolidated_Historical_Data'!E16/'02_Consolidated_Historical_Data'!E7 -> 0.18713934 | F12: ='02_Consolidated_Historical_Data'!F16/'02_Consolidated_Historical_Data'!F7 -> 0.19328422
A13: PAT Margin % | B13: ='02_Consolidated_Historical_Data'!B26/'02_Consolidated_Historical_Data'!B7 -> 0.094557487 | C13: ='02_Consolidated_Historical_Data'!C26/'02_Consolidated_Historical_Data'!C7 -> 0.083998928 | D13: ='02_Consolidated_Historical_Data'!D26/'02_Consolidated_Historical_Data'!D7 -> 0.086410519 | E13: ='02_Consolidated_Historical_Data'!E26/'02_Consolidated_Historical_Data'!E7 -> 0.082956855 | F13: ='02_Consolidated_Historical_Data'!F26/'02_Consolidated_Historical_Data'!F7 -> 0.089017594
A14: EBIT Margin % | B14: =B9/'02_Consolidated_Historical_Data'!B7 -> 0.13415836 | C14: =C9/'02_Consolidated_Historical_Data'!C7 -> 0.12954671 | D14: =D9/'02_Consolidated_Historical_Data'!D7 -> 0.13937879 | E14: =E9/'02_Consolidated_Historical_Data'!E7 -> 0.13292645 | F14: =F9/'02_Consolidated_Historical_Data'!F7 -> 0.13965464
A16: Return Ratios | B16: FY 2021-22 | C16: FY 2022-23 | D16: FY 2023-24 | E16: FY 2024-25 | F16: FY 2025-26
A17: ROE % | B17: ='02_Consolidated_Historical_Data'!B26/('03_Consolidated_Balance_Sheet_'!J11-'03_Consolidated_Balance_Sheet_'!J10) -> 0.10259065 | C17: ='02_Consolidated_Historical_Data'!C26/('03_Consolidated_Balance_Sheet_'!K11-'03_Consolidated_Balance_Sheet_'!K10) -> 0.11013934 | D17: ='02_Consolidated_Historical_Data'!D26/('03_Consolidated_Balance_Sheet_'!L11-'03_Consolidated_Balance_Sheet_'!L10) -> 0.10024064 | E17: ='02_Consolidated_Historical_Data'!E26/('03_Consolidated_Balance_Sheet_'!M11-'03_Consolidated_Balance_Sheet_'!M10) -> 0.09642908 | F17: ='02_Consolidated_Historical_Data'!F26/('03_Consolidated_Balance_Sheet_'!N11-'03_Consolidated_Balance_Sheet_'!N10) -> 0.10591905
A18: Calculated ROCE % | B18: =B9/('03_Consolidated_Balance_Sheet_'!J11+'03_Consolidated_Balance_Sheet_'!J19) -> 0.085027278 | C18: =C9/('03_Consolidated_Balance_Sheet_'!K11+'03_Consolidated_Balance_Sheet_'!K19) -> 0.095719308 | D18: =D9/('03_Consolidated_Balance_Sheet_'!L11+'03_Consolidated_Balance_Sheet_'!L19) -> 0.094957263 | E18: =E9/('03_Consolidated_Balance_Sheet_'!M11+'03_Consolidated_Balance_Sheet_'!M19) -> 0.087067223 | F18: =F9/('03_Consolidated_Balance_Sheet_'!N11+'03_Consolidated_Balance_Sheet_'!N19) -> 0.091773648
A19: ROA % | B19: ='02_Consolidated_Historical_Data'!B26/'03_Consolidated_Balance_Sheet_'!B27 -> 0.050332181 | C19: ='02_Consolidated_Historical_Data'!C26/'03_Consolidated_Balance_Sheet_'!C27 -> 0.048583995 | D19: ='02_Consolidated_Historical_Data'!D26/'03_Consolidated_Balance_Sheet_'!D27 -> 0.04800592 | E19: ='02_Consolidated_Historical_Data'!E26/'03_Consolidated_Balance_Sheet_'!E27 -> 0.041694336 | F19: ='02_Consolidated_Historical_Data'!F26/'03_Consolidated_Balance_Sheet_'!F27 -> 0.043961362
A21: Leverage Ratios (₹ Crore) | B21: FY 2021-22 | C21: FY 2022-23 | D21: FY 2023-24 | E21: FY 2024-25 | F21: FY 2025-26
A22: Total Debt | B22: ='03_Consolidated_Balance_Sheet_'!J14+'03_Consolidated_Balance_Sheet_'!J22 -> 224623 | C22: ='03_Consolidated_Balance_Sheet_'!K14+'03_Consolidated_Balance_Sheet_'!K22 -> 272395 | D22: ='03_Consolidated_Balance_Sheet_'!L14+'03_Consolidated_Balance_Sheet_'!L22 -> 327865 | E22: ='03_Consolidated_Balance_Sheet_'!M14+'03_Consolidated_Balance_Sheet_'!M22 -> 347530 | F22: ='03_Consolidated_Balance_Sheet_'!N14+'03_Consolidated_Balance_Sheet_'!N22 -> 374421
A23: Cash and Cash Equivalent | B23: ='03_Consolidated_Balance_Sheet_'!B22 -> 36178 | C23: ='03_Consolidated_Balance_Sheet_'!C22 -> 6851 | D23: ='03_Consolidated_Balance_Sheet_'!D22 -> 10211 | E23: ='03_Consolidated_Balance_Sheet_'!E22 -> 106502 | F23: ='03_Consolidated_Balance_Sheet_'!F22 -> 145977
A25: Net Debt | B25: =B22-B23 -> 188445 | C25: =C22-C23 -> 265544 | D25: =D22-D23 -> 317654 | E25: =E22-E23 -> 241028 | F25: =F22-F23 -> 228444
A27: Debt/EBITDA | B27: =B22/'02_Consolidated_Historical_Data'!B16 -> 1.8161039 | C27: =C22/'02_Consolidated_Historical_Data'!C16 -> 1.769718 | D27: =D22/'02_Consolidated_Historical_Data'!D16 -> 1.8389422 | E27: =E22/'02_Consolidated_Historical_Data'!E16 -> 1.8947018 | F27: =F22/'02_Consolidated_Historical_Data'!F16 -> 1.8008715
A28: Net Debt/EBITDA | B28: =B25/'02_Consolidated_Historical_Data'!B16 -> 1.5236005 | C28: =C25/'02_Consolidated_Historical_Data'!C16 -> 1.7252079 | D28: =D25/'02_Consolidated_Historical_Data'!D16 -> 1.7816703 | E28: =E25/'02_Consolidated_Historical_Data'!E16 -> 1.3140627 | F28: =F25/'02_Consolidated_Historical_Data'!F16 -> 1.0987586
A29: Interest Coverage Ratio | B29: =B9/'02_Consolidated_Historical_Data'!B19 -> 6.4386999 | C29: =C9/'02_Consolidated_Historical_Data'!C19 -> 5.8053753 | D29: =D9/'02_Consolidated_Historical_Data'!D19 -> 5.5133662 | E29: =E9/'02_Consolidated_Historical_Data'!E19 -> 5.3684124 | F29: =F9/'02_Consolidated_Historical_Data'!F19 -> 5.551273
A31: Working Capital Analysis (₹ Crore) | B31: FY 2021-22 | C31: FY 2022-23 | D31: FY 2023-24 | E31: FY 2024-25 | F31: FY 2025-26
A32: Inventories Days | B32: ='03_Consolidated_Balance_Sheet_'!B19/'02_Consolidated_Historical_Data'!B7*365 -> 56.184533 | C32: ='03_Consolidated_Balance_Sheet_'!C19/'02_Consolidated_Historical_Data'!C7*365 -> 58.728112 | D32: ='03_Consolidated_Balance_Sheet_'!D19/'02_Consolidated_Historical_Data'!D7*365 -> 57.583956 | E32: ='03_Consolidated_Balance_Sheet_'!E19/'02_Consolidated_Historical_Data'!E7*365 -> 54.393094 | F32: ='03_Consolidated_Balance_Sheet_'!F19/'02_Consolidated_Historical_Data'!F7*365 -> 56.646724
A33: Receivable Days | B33: ='03_Consolidated_Balance_Sheet_'!B21/'02_Consolidated_Historical_Data'!B7*365 -> 9.7907446 | C33: ='03_Consolidated_Balance_Sheet_'!C21/'02_Consolidated_Historical_Data'!C7*365 -> 8.244842 | D33: ='03_Consolidated_Balance_Sheet_'!D21/'02_Consolidated_Historical_Data'!D7*365 -> 8.5455323 | E33: ='03_Consolidated_Balance_Sheet_'!E21/'02_Consolidated_Historical_Data'!E7*365 -> 15.685747 | F33: ='03_Consolidated_Balance_Sheet_'!F21/'02_Consolidated_Historical_Data'!F7*365 -> 19.847273
A34: Payable Days | B34: ='03_Consolidated_Balance_Sheet_'!J24/'02_Consolidated_Historical_Data'!B7*365 -> 53.425394 | C34: ='03_Consolidated_Balance_Sheet_'!K24/'02_Consolidated_Historical_Data'!C7*365 -> 59.140542 | D34: ='03_Consolidated_Balance_Sheet_'!L24/'02_Consolidated_Historical_Data'!D7*365 -> 53.050154 | E34: ='03_Consolidated_Balance_Sheet_'!M24/'02_Consolidated_Historical_Data'!E7*365 -> 69.559719 | F34: ='03_Consolidated_Balance_Sheet_'!N24/'02_Consolidated_Historical_Data'!F7*365 -> 53.898557
A35: Cash Conversion Cycle (CCC) | B35: =B32+B33-B34 -> 12.549883 | C35: =C32+C33-C34 -> 7.8324126 | D35: =D32+D33-D34 -> 13.079334 | E35: =E32+E33-E34 -> 0.51912184 | F35: =F32+F33-F34 -> 22.59544
A36: Net Working Capital (NWC) | B36: ='03_Consolidated_Balance_Sheet_'!B19+'03_Consolidated_Balance_Sheet_'!B21-'03_Consolidated_Balance_Sheet_'!J24 -> 24066 | C36: ='03_Consolidated_Balance_Sheet_'!C19+'03_Consolidated_Balance_Sheet_'!C21-'03_Consolidated_Balance_Sheet_'!K24 -> 18820 | D36: ='03_Consolidated_Balance_Sheet_'!D19+'03_Consolidated_Balance_Sheet_'!D21-'03_Consolidated_Balance_Sheet_'!L24 -> 32769 | E36: =-('03_Consolidated_Balance_Sheet_'!E19+'03_Consolidated_Balance_Sheet_'!E21-'03_Consolidated_Balance_Sheet_'!M24) -> -1394 | F36: ='03_Consolidated_Balance_Sheet_'!F19+'03_Consolidated_Balance_Sheet_'!F21-'03_Consolidated_Balance_Sheet_'!N24 -> 66590
A37: Working Capital/ Revenue % | B37: =B36/'02_Consolidated_Historical_Data'!B7 -> 0.034383242 | C37: =C36/'02_Consolidated_Historical_Data'!C7 -> 0.021458665 | D37: =D36/'02_Consolidated_Historical_Data'!D7 -> 0.035833793 | E37: =E36/'02_Consolidated_Historical_Data'!E7 -> -0.0014222516 | F37: =F36/'02_Consolidated_Historical_Data'!F7 -> 0.061905315
A39: Cash Flow Analysis (₹ Crore) | B39: FY 2021-22 | C39: FY 2022-23 | D39: FY 2023-24 | E39: FY 2024-25 | F39: FY 2025-26
A40: Free Cash Flow (FCF) | B40: ='04_Consolidated_Cash_Flow'!B6+'04_Consolidated_Cash_Flow'!B8 -> 1492 | C40: ='04_Consolidated_Cash_Flow'!C6+'04_Consolidated_Cash_Flow'!C8 -> 22019 | D40: ='04_Consolidated_Cash_Flow'!D6+'04_Consolidated_Cash_Flow'!D8 -> 5905 | E40: ='04_Consolidated_Cash_Flow'!E6+'04_Consolidated_Cash_Flow'!E8 -> 38736 | F40: ='04_Consolidated_Cash_Flow'!F6+'04_Consolidated_Cash_Flow'!F8 -> 69197
A41: FCF Margin % | B41: =B40/'02_Consolidated_Historical_Data'!B7 -> 0.0021316296 | C41: =C40/'02_Consolidated_Historical_Data'!C7 -> 0.025106182 | D41: =D40/'02_Consolidated_Historical_Data'!D7 -> 0.0064572781 | E41: =E40/'02_Consolidated_Historical_Data'!E7 -> 0.039521046 | F41: =F40/'02_Consolidated_Historical_Data'!F7 -> 0.06432891
A42: CFO / EBITDA % | B42: ='04_Consolidated_Cash_Flow'!B6/'02_Consolidated_Historical_Data'!B16 -> 0.89465088 | C42: ='04_Consolidated_Cash_Flow'!C6/'02_Consolidated_Historical_Data'!C16 -> 0.74727131 | D42: ='04_Consolidated_Cash_Flow'!D6/'02_Consolidated_Historical_Data'!D16 -> 0.89061641 | E42: ='04_Consolidated_Cash_Flow'!E6/'02_Consolidated_Historical_Data'!E16 -> 0.97427244 | F42: ='04_Consolidated_Cash_Flow'!F6/'02_Consolidated_Historical_Data'!F16 -> 0.92401556
A43: CAPEX / Revenue % | B43: =-'04_Consolidated_Cash_Flow'!B8/'02_Consolidated_Historical_Data'!B7 -> 0.15596042 | C43: =-'04_Consolidated_Cash_Flow'!C8/'02_Consolidated_Historical_Data'!C7 -> 0.10604024 | D43: =-'04_Consolidated_Cash_Flow'!D8/'02_Consolidated_Historical_Data'!D7 -> 0.16718172 | E43: =-'04_Consolidated_Cash_Flow'!E8/'02_Consolidated_Historical_Data'!E7 -> 0.14280365 | F43: =-'04_Consolidated_Cash_Flow'!F8/'02_Consolidated_Historical_Data'!F7 -> 0.11426871
A44: FCF Conversion % | B44: =B40/'04_Consolidated_Cash_Flow'!B6 -> 0.013483471 | C44: =C40/'04_Consolidated_Cash_Flow'!C6 -> 0.19143627 | D44: =D40/'04_Consolidated_Cash_Flow'!D6 -> 0.037187949 | E44: =E40/'04_Consolidated_Cash_Flow'!E6 -> 0.21676189 | F44: =F40/'04_Consolidated_Cash_Flow'!F6 -> 0.36018906
A46: Segment Mix Analysis | B46: FY 2021-22 | C46: FY 2022-23 | D46: FY 2023-24 | E46: FY 2024-25 | F46: FY 2025-26
A47: Segment Revenue Contribution %
A48: Oil-to-Chemicals (O2C) % | B48: ='05_Segment_Historical_Raw_Data'!B7/('05_Segment_Historical_Raw_Data'!B7+'05_Segment_Historical_Raw_Data'!B21+'05_Segment_Historical_Raw_Data'!B35+'05_Segment_Historical_Raw_Data'!B48) -> 0.65947335 | C48: ='05_Segment_Historical_Raw_Data'!C7/('05_Segment_Historical_Raw_Data'!C7+'05_Segment_Historical_Raw_Data'!C21+'05_Segment_Historical_Raw_Data'!C35+'05_Segment_Historical_Raw_Data'!C48) -> 0.6169899 | D48: ='05_Segment_Historical_Raw_Data'!D7/('05_Segment_Historical_Raw_Data'!D7+'05_Segment_Historical_Raw_Data'!D21+'05_Segment_Historical_Raw_Data'!D35+'05_Segment_Historical_Raw_Data'!D48) -> 0.54896569 | E48: ='05_Segment_Historical_Raw_Data'!E7/('05_Segment_Historical_Raw_Data'!E7+'05_Segment_Historical_Raw_Data'!E21+'05_Segment_Historical_Raw_Data'!E35+'05_Segment_Historical_Raw_Data'!E48) -> 0.55128764 | F48: ='05_Segment_Historical_Raw_Data'!F7/('05_Segment_Historical_Raw_Data'!F7+'05_Segment_Historical_Raw_Data'!F21+'05_Segment_Historical_Raw_Data'!F35+'05_Segment_Historical_Raw_Data'!F48) -> 0.53700453
A49: Digital Services (Jio) % | B49: ='05_Segment_Historical_Raw_Data'!B21/('05_Segment_Historical_Raw_Data'!B7+'05_Segment_Historical_Raw_Data'!B21+'05_Segment_Historical_Raw_Data'!B35+'05_Segment_Historical_Raw_Data'!B48) -> 0.10671135 | C49: ='05_Segment_Historical_Raw_Data'!C21/('05_Segment_Historical_Raw_Data'!C7+'05_Segment_Historical_Raw_Data'!C21+'05_Segment_Historical_Raw_Data'!C35+'05_Segment_Historical_Raw_Data'!C48) -> 0.11246771 | D49: ='05_Segment_Historical_Raw_Data'!D21/('05_Segment_Historical_Raw_Data'!D7+'05_Segment_Historical_Raw_Data'!D21+'05_Segment_Historical_Raw_Data'!D35+'05_Segment_Historical_Raw_Data'!D48) -> 0.12922272 | E49: ='05_Segment_Historical_Raw_Data'!E21/('05_Segment_Historical_Raw_Data'!E7+'05_Segment_Historical_Raw_Data'!E21+'05_Segment_Historical_Raw_Data'!E35+'05_Segment_Historical_Raw_Data'!E48) -> 0.13552569 | F49: ='05_Segment_Historical_Raw_Data'!F21/('05_Segment_Historical_Raw_Data'!F7+'05_Segment_Historical_Raw_Data'!F21+'05_Segment_Historical_Raw_Data'!F35+'05_Segment_Historical_Raw_Data'!F48) -> 0.1428151
A50: Organised Retail % | B50: ='05_Segment_Historical_Raw_Data'!B35/('05_Segment_Historical_Raw_Data'!B7+'05_Segment_Historical_Raw_Data'!B21+'05_Segment_Historical_Raw_Data'!B35+'05_Segment_Historical_Raw_Data'!B48) -> 0.22539777 | C50: ='05_Segment_Historical_Raw_Data'!C35/('05_Segment_Historical_Raw_Data'!C7+'05_Segment_Historical_Raw_Data'!C21+'05_Segment_Historical_Raw_Data'!C35+'05_Segment_Historical_Raw_Data'!C48) -> 0.25441178 | D50: ='05_Segment_Historical_Raw_Data'!D35/('05_Segment_Historical_Raw_Data'!D7+'05_Segment_Historical_Raw_Data'!D21+'05_Segment_Historical_Raw_Data'!D35+'05_Segment_Historical_Raw_Data'!D48) -> 0.2982121 | E50: ='05_Segment_Historical_Raw_Data'!E35/('05_Segment_Historical_Raw_Data'!E7+'05_Segment_Historical_Raw_Data'!E21+'05_Segment_Historical_Raw_Data'!E35+'05_Segment_Historical_Raw_Data'!E48) -> 0.29101719 | F50: ='05_Segment_Historical_Raw_Data'!F35/('05_Segment_Historical_Raw_Data'!F7+'05_Segment_Historical_Raw_Data'!F21+'05_Segment_Historical_Raw_Data'!F35+'05_Segment_Historical_Raw_Data'!F48) -> 0.30083639
A51: Oil & Gas (E&P) % | B51: ='05_Segment_Historical_Raw_Data'!B48/('05_Segment_Historical_Raw_Data'!B48+'05_Segment_Historical_Raw_Data'!B35+'05_Segment_Historical_Raw_Data'!B21+'05_Segment_Historical_Raw_Data'!B7) -> 0.0084175407 | C51: ='05_Segment_Historical_Raw_Data'!C48/('05_Segment_Historical_Raw_Data'!C48+'05_Segment_Historical_Raw_Data'!C35+'05_Segment_Historical_Raw_Data'!C21+'05_Segment_Historical_Raw_Data'!C7) -> 0.016130608 | D51: ='05_Segment_Historical_Raw_Data'!D48/('05_Segment_Historical_Raw_Data'!D48+'05_Segment_Historical_Raw_Data'!D35+'05_Segment_Historical_Raw_Data'!D21+'05_Segment_Historical_Raw_Data'!D7) -> 0.023599491 | E51: ='05_Segment_Historical_Raw_Data'!E48/('05_Segment_Historical_Raw_Data'!E48+'05_Segment_Historical_Raw_Data'!E35+'05_Segment_Historical_Raw_Data'!E21+'05_Segment_Historical_Raw_Data'!E7) -> 0.02216948 | F51: ='05_Segment_Historical_Raw_Data'!F48/('05_Segment_Historical_Raw_Data'!F48+'05_Segment_Historical_Raw_Data'!F35+'05_Segment_Historical_Raw_Data'!F21+'05_Segment_Historical_Raw_Data'!F7) -> 0.01934397
A53: Segment EBITDA Contribution %
A54: Oil-to-Chemicals (O2C) % | B54: ='05_Segment_Historical_Raw_Data'!B9/('05_Segment_Historical_Raw_Data'!B9+'05_Segment_Historical_Raw_Data'!B24+'05_Segment_Historical_Raw_Data'!B37+'05_Segment_Historical_Raw_Data'!B49) -> 0.572118 | C54: ='05_Segment_Historical_Raw_Data'!C9/('05_Segment_Historical_Raw_Data'!C9+'05_Segment_Historical_Raw_Data'!C24+'05_Segment_Historical_Raw_Data'!C37+'05_Segment_Historical_Raw_Data'!C49) -> 0.43517059 | D54: ='05_Segment_Historical_Raw_Data'!D9/('05_Segment_Historical_Raw_Data'!D9+'05_Segment_Historical_Raw_Data'!D24+'05_Segment_Historical_Raw_Data'!D37+'05_Segment_Historical_Raw_Data'!D49) -> 0.38568629 | E54: ='05_Segment_Historical_Raw_Data'!E9/('05_Segment_Historical_Raw_Data'!E9+'05_Segment_Historical_Raw_Data'!E24+'05_Segment_Historical_Raw_Data'!E37+'05_Segment_Historical_Raw_Data'!E49) -> 0.33071311 | F54: ='05_Segment_Historical_Raw_Data'!F9/('05_Segment_Historical_Raw_Data'!F9+'05_Segment_Historical_Raw_Data'!F24+'05_Segment_Historical_Raw_Data'!F37+'05_Segment_Historical_Raw_Data'!F49) -> 0.33050931
A55: Digital Services (Jio) % | B55: ='05_Segment_Historical_Raw_Data'!B24/('05_Segment_Historical_Raw_Data'!B24+'05_Segment_Historical_Raw_Data'!B37+'05_Segment_Historical_Raw_Data'!B49+'05_Segment_Historical_Raw_Data'!B9) -> 0.29482714 | C55: ='05_Segment_Historical_Raw_Data'!C24/('05_Segment_Historical_Raw_Data'!C24+'05_Segment_Historical_Raw_Data'!C37+'05_Segment_Historical_Raw_Data'!C49+'05_Segment_Historical_Raw_Data'!C9) -> 0.34407111 | D55: ='05_Segment_Historical_Raw_Data'!D24/('05_Segment_Historical_Raw_Data'!D24+'05_Segment_Historical_Raw_Data'!D37+'05_Segment_Historical_Raw_Data'!D49+'05_Segment_Historical_Raw_Data'!D9) -> 0.35036257 | E55: ='05_Segment_Historical_Raw_Data'!E24/('05_Segment_Historical_Raw_Data'!E24+'05_Segment_Historical_Raw_Data'!E37+'05_Segment_Historical_Raw_Data'!E49+'05_Segment_Historical_Raw_Data'!E9) -> 0.39093408 | F55: ='05_Segment_Historical_Raw_Data'!F24/('05_Segment_Historical_Raw_Data'!F24+'05_Segment_Historical_Raw_Data'!F37+'05_Segment_Historical_Raw_Data'!F49+'05_Segment_Historical_Raw_Data'!F9) -> 0.41792674
A56: Organised Retail % | B56: ='05_Segment_Historical_Raw_Data'!B37/('05_Segment_Historical_Raw_Data'!B37+'05_Segment_Historical_Raw_Data'!B24+'05_Segment_Historical_Raw_Data'!B49+'05_Segment_Historical_Raw_Data'!B9) -> 0.092350725 | C56: ='05_Segment_Historical_Raw_Data'!C37/('05_Segment_Historical_Raw_Data'!C37+'05_Segment_Historical_Raw_Data'!C24+'05_Segment_Historical_Raw_Data'!C49+'05_Segment_Historical_Raw_Data'!C9) -> 0.12557524 | D56: ='05_Segment_Historical_Raw_Data'!D37/('05_Segment_Historical_Raw_Data'!D37+'05_Segment_Historical_Raw_Data'!D24+'05_Segment_Historical_Raw_Data'!D49+'05_Segment_Historical_Raw_Data'!D9) -> 0.14243235 | E56: ='05_Segment_Historical_Raw_Data'!E37/('05_Segment_Historical_Raw_Data'!E37+'05_Segment_Historical_Raw_Data'!E24+'05_Segment_Historical_Raw_Data'!E49+'05_Segment_Historical_Raw_Data'!E9) -> 0.15092229 | F56: ='05_Segment_Historical_Raw_Data'!F37/('05_Segment_Historical_Raw_Data'!F37+'05_Segment_Historical_Raw_Data'!F24+'05_Segment_Historical_Raw_Data'!F49+'05_Segment_Historical_Raw_Data'!F9) -> 0.14757356
A57: Oil & Gas (E&P) % | B57: ='05_Segment_Historical_Raw_Data'!B49/('05_Segment_Historical_Raw_Data'!B49+'05_Segment_Historical_Raw_Data'!B37+'05_Segment_Historical_Raw_Data'!B24+'05_Segment_Historical_Raw_Data'!B9) -> 0.040704136 | C57: ='05_Segment_Historical_Raw_Data'!C49/('05_Segment_Historical_Raw_Data'!C49+'05_Segment_Historical_Raw_Data'!C37+'05_Segment_Historical_Raw_Data'!C24+'05_Segment_Historical_Raw_Data'!C9) -> 0.095183061 | D57: ='05_Segment_Historical_Raw_Data'!D49/('05_Segment_Historical_Raw_Data'!D49+'05_Segment_Historical_Raw_Data'!D37+'05_Segment_Historical_Raw_Data'!D24+'05_Segment_Historical_Raw_Data'!D9) -> 0.12151878 | E57: ='05_Segment_Historical_Raw_Data'!E49/('05_Segment_Historical_Raw_Data'!E49+'05_Segment_Historical_Raw_Data'!E37+'05_Segment_Historical_Raw_Data'!E24+'05_Segment_Historical_Raw_Data'!E9) -> 0.12743052 | F57: ='05_Segment_Historical_Raw_Data'!F49/('05_Segment_Historical_Raw_Data'!F49+'05_Segment_Historical_Raw_Data'!F37+'05_Segment_Historical_Raw_Data'!F24+'05_Segment_Historical_Raw_Data'!F9) -> 0.10399039

Sheet 07_Forecast_assumptions
A1: RELIANCE INDUSTRIES LIMITED
A2: FORECAST ASSUMPTIONS & DRIVERS (SCENERIO ENGINE) | C2: Master Scenario Switch ID: | D2: 2 | E2: =CHOOSE(D2, "BULL CASE", "BASE CASE", "BEAR CASE") -> BASE CASE
A4: Segment Metrics & Operational Drivers | B4: Unit(s) | C4: FY 2026-27 | D4: FY 2027-28 | E4: FY 2028-29 | F4: FY 2029-30 | G4: FY 2030-31
A5: Corporate Assumptions | I5: Notes
A6: Tax Rate | B6: % | C6: 25.17 | D6: 25.17 | E6: 25.17 | F6: 25.17 | G6: 25.17 | I6: Normalized effective tax rate based on historical average; maintained constant for forecast period
A7: WACC (Active Dynamic Target) | B7: % | C7: =CHOOSE($D$2,C8,C9,C10) -> 10.5 | D7: =CHOOSE($D$2,D8,D9,D10) -> 10.5 | E7: =CHOOSE($D$2,E8,E9,E10) -> 10.5 | F7: =CHOOSE($D$2,F8,F9,F10) -> 10.5 | G7: =CHOOSE($D$2,G8,G9,G10) -> 10.5 | I7: Long-term weighted average cost of capital assumption reflecting Reliance's diversified business mix and risk profile
A8: ├── Bull Case Scenario | B8: % | C8: =C9-0.75 -> 9.75 | D8: =D9-0.75 -> 9.75 | E8: =E9-0.75 -> 9.75 | F8: =F9-0.75 -> 9.75 | G8: =G9-0.75 -> 9.75
A9: ├── Base Case Scenario | B9: % | C9: 10.5 | D9: 10.5 | E9: 10.5 | F9: 10.5 | G9: 10.5
A10: ├── Bear Case Scenario | B10: % | C10: =C9+0.75 -> 11.25 | D10: =D9+0.75 -> 11.25 | E10: =E9+0.75 -> 11.25 | F10: =F9+0.75 -> 11.25 | G10: =G9+0.75 -> 11.25
A11: Terminal Growth Rate (Active) | B11: % | C11: =CHOOSE($D$2,C12,C13,C14) -> 5 | D11: =CHOOSE($D$2,D12,D13,D14) -> 5 | E11: =CHOOSE($D$2,E12,E13,E14) -> 5 | F11: =CHOOSE($D$2,F12,F13,F14) -> 5 | G11: =CHOOSE($D$2,G12,G13,G14) -> 5 | I11: Long-term nominal growth assumption reflecting mature business growth plus inflation
A12: ├── Bull Case Scenario | B12: % | C12: =C13+0.5 -> 5.5 | D12: =D13+0.5 -> 5.5 | E12: =E13+0.5 -> 5.5 | F12: =F13+0.5 -> 5.5 | G12: =G13+0.5 -> 5.5
A13: ├── Base Case Scenario | B13: % | C13: =C14+0.5 -> 5 | D13: =D14+0.5 -> 5 | E13: =E14+0.5 -> 5 | F13: =F14+0.5 -> 5 | G13: =G14+0.5 -> 5
A14: ├── Bear Case Scenario | B14: % | C14: 4.5 | D14: 4.5 | E14: 4.5 | F14: 4.5 | G14: 4.5
A15: Active Conglomerate Discount | B15: % | C15: =CHOOSE($D$2,C16,C17,C18) -> -5 | D15: =CHOOSE($D$2,D16,D17,D18) -> -5 | E15: =CHOOSE($D$2,E16,E17,E18) -> -5 | F15: =CHOOSE($D$2,F16,F17,F18) -> -5 | G15: =CHOOSE($D$2,G16,G17,G18) -> -5
A16: ├── Bull Case Scenario | B16: % | C16: =C17+5 -> 0 | D16: =D17+5 -> 0 | E16: =E17+5 -> 0 | F16: =F17+5 -> 0 | G16: =G17+5 -> 0
A17: ├── Base Case Scenario | B17: % | C17: -5 | D17: -5 | E17: -5 | F17: -5 | G17: -5
A18: ├── Bear Case Scenario | B18: % | C18: =C17-5 -> -10 | D18: =D17-5 -> -10 | E18: =E17-5 -> -10 | F18: =F17-5 -> -10 | G18: =G17-5 -> -10
A20: Oil-to-Chemicals (O2C)
A21: Revenue Growth (Active) | B21: % | C21: =CHOOSE($D$2,C22,C23,C24) -> 0.035435396 | D21: =CHOOSE($D$2,D22,D23,D24) -> 0.035435396 | E21: =CHOOSE($D$2,E22,E23,E24) -> 0.035435396 | F21: =CHOOSE($D$2,F22,F23,F24) -> 0.035435396 | G21: =CHOOSE($D$2,G22,G23,G24) -> 0.035435396 | I21: Based on historical normalized growth trend; mature refining and petrochemical segment with limited volume expansion
A22: ├── Bull Case Scenario | B22: % | C22: =C23+1% -> 0.045435396 | D22: =D23+1% -> 0.045435396 | E22: =E23+1% -> 0.045435396 | F22: =F23+1% -> 0.045435396 | G22: =G23+1% -> 0.045435396
A23: ├── Base Case Scenario | B23: % | C23: =AVERAGE('05_Segment_Historical_Raw_Data'!$C8:$F8) -> 0.035435396 | D23: =AVERAGE('05_Segment_Historical_Raw_Data'!$C8:$F8) -> 0.035435396 | E23: =AVERAGE('05_Segment_Historical_Raw_Data'!$C8:$F8) -> 0.035435396 | F23: =AVERAGE('05_Segment_Historical_Raw_Data'!$C8:$F8) -> 0.035435396 | G23: =AVERAGE('05_Segment_Historical_Raw_Data'!$C8:$F8) -> 0.035435396
A24: ├── Bear Case Scenario | B24: % | C24: =C23-1% -> 0.025435396 | D24: =D23-1% -> 0.025435396 | E24: =E23-1% -> 0.025435396 | F24: =F23-1% -> 0.025435396 | G24: =G23-1% -> 0.025435396
A25: EBITDA Margin (Active) | B25: % | C25: =CHOOSE($D$2,C26,C27,C28) -> 0.096995115 | D25: =CHOOSE($D$2,D26,D27,D28) -> 0.096995115 | E25: =CHOOSE($D$2,E26,E27,E28) -> 0.096995115 | F25: =CHOOSE($D$2,F26,F27,F28) -> 0.096995115 | G25: =CHOOSE($D$2,G26,G27,G28) -> 0.096995115 | I25: Normalized historical EBITDA margin excluding commodity peak years; assumes mid-cycle profitability
A26: ├── Bull Case Scenario | B26: % | C26: =C27+2% -> 0.11699512 | D26: =D27+2% -> 0.11699512 | E26: =E27+2% -> 0.11699512 | F26: =F27+2% -> 0.11699512 | G26: =G27+2% -> 0.11699512
A27: ├── Base Case Scenario | B27: % | C27: =AVERAGE('05_Segment_Historical_Raw_Data'!$C10:$F10) -> 0.096995115 | D27: =AVERAGE('05_Segment_Historical_Raw_Data'!$C10:$F10) -> 0.096995115 | E27: =AVERAGE('05_Segment_Historical_Raw_Data'!$C10:$F10) -> 0.096995115 | F27: =AVERAGE('05_Segment_Historical_Raw_Data'!$C10:$F10) -> 0.096995115 | G27: =AVERAGE('05_Segment_Historical_Raw_Data'!$C10:$F10) -> 0.096995115
A28: ├── Bear Case Scenario | B28: % | C28: =C27-2% -> 0.076995115 | D28: =D27-2% -> 0.076995115 | E28: =E27-2% -> 0.076995115 | F28: =F27-2% -> 0.076995115 | G28: =G27-2% -> 0.076995115
A29: Active O2C Multiple | B29: x | C29: =CHOOSE($D$2,C30,C31,C32) -> 6.5 | D29: =CHOOSE($D$2,D30,D31,D32) -> 6.5 | E29: =CHOOSE($D$2,E30,E31,E32) -> 6.5 | F29: =CHOOSE($D$2,F30,F31,F32) -> 6.5 | G29: =CHOOSE($D$2,G30,G31,G32) -> 6.5 | I29: Premium to Indian Oil's observed multiple, which is used as a reference rather than a direct like-for-like
A30: ├── Bull Case Scenario | B30: x | C30: =C31+1 -> 7.5 | D30: =D31+1 -> 7.5 | E30: =E31+1 -> 7.5 | F30: =F31+1 -> 7.5 | G30: =G31+1 -> 7.5 | I30: benchmark given differences in ownership scale, integration and business mix. The premium reflects Reliance's
A31: ├── Base Case Scenario | B31: x | C31: 6.5 | D31: 6.5 | E31: 6.5 | F31: 6.5 | G31: 6.5 | I31: integrated refining and petrochemical platform,asset complexity, private-sector capital allocation and broader downstream capabilities.
A32: ├── Bear Case Scenario | B32: x | C32: =C31-1 -> 5.5 | D32: =D31-1 -> 5.5 | E32: =E31-1 -> 5.5 | F32: =F31-1 -> 5.5 | G32: =G31-1 -> 5.5
A33: EBIT Margin | B33: % | C33: =AVERAGE('05_Segment_Historical_Raw_Data'!$C12:$F12) -> 0.082568641 | D33: =AVERAGE('05_Segment_Historical_Raw_Data'!$C12:$F12) -> 0.082568641 | E33: =AVERAGE('05_Segment_Historical_Raw_Data'!$C12:$F12) -> 0.082568641 | F33: =AVERAGE('05_Segment_Historical_Raw_Data'!$C12:$F12) -> 0.082568641 | G33: =AVERAGE('05_Segment_Historical_Raw_Data'!$C12:$F12) -> 0.082568641 | I33: Derived from normalized EBITDA margin after depreciation assumptions
A34: GRM Assumption ($/bbl) (Active) | B34: $/bbl | C34: =CHOOSE($D$2,C35,C36,C37) -> 10.78 | D34: =CHOOSE($D$2,D35,D36,D37) -> 10.78 | E34: =CHOOSE($D$2,E35,E36,E37) -> 10.78 | F34: =CHOOSE($D$2,F35,F36,F37) -> 10.78 | G34: =CHOOSE($D$2,G35,G36,G37) -> 10.78 | I34: Historical average Gross Refining Margin used as normalized mid-cycle assumption
A35: ├── Bull Case Scenario | B35: $/bbl | C35: =C36+2.25 -> 13.03 | D35: =D36+2.25 -> 13.03 | E35: =E36+2.25 -> 13.03 | F35: =F36+2.25 -> 13.03 | G35: =G36+2.25 -> 13.03
A36: ├── Base Case Scenario | B36: $/bbl | C36: =AVERAGE('05_Segment_Historical_Raw_Data'!$B17:$F17) -> 10.78 | D36: =AVERAGE('05_Segment_Historical_Raw_Data'!$B17:$F17) -> 10.78 | E36: =AVERAGE('05_Segment_Historical_Raw_Data'!$B17:$F17) -> 10.78 | F36: =AVERAGE('05_Segment_Historical_Raw_Data'!$B17:$F17) -> 10.78 | G36: =AVERAGE('05_Segment_Historical_Raw_Data'!$B17:$F17) -> 10.78
A37: ├── Bear Case Scenario | B37: $/bbl | C37: =C36-2.25 -> 8.53 | D37: =D36-2.25 -> 8.53 | E37: =E36-2.25 -> 8.53 | F37: =F36-2.25 -> 8.53 | G37: =G36-2.25 -> 8.53
A38: CAPEX / Revenue (Active) | B38: % | C38: =CHOOSE($D$2,C39,C40,C41) -> 0.048860132 | D38: =CHOOSE($D$2,D39,D40,D41) -> 0.048860132 | E38: =CHOOSE($D$2,E39,E40,E41) -> 0.048860132 | F38: =CHOOSE($D$2,F39,F40,F41) -> 0.048860132 | G38: =CHOOSE($D$2,G39,G40,G41) -> 0.048860132 | I38: Maintenance and efficiency improvement CAPEX based on normalized historical CAPEX intensity
A39: ├── Bull Case Scenario | B39: % | C39: =C40+1% -> 0.058860132 | D39: =D40+1% -> 0.058860132 | E39: =E40+1% -> 0.058860132 | F39: =F40+1% -> 0.058860132 | G39: =G40+1% -> 0.058860132
A40: ├── Base Case Scenario | B40: % | C40: ='05_Segment_Historical_Raw_Data'!$F13/'05_Segment_Historical_Raw_Data'!$F7 -> 0.048860132 | D40: ='05_Segment_Historical_Raw_Data'!$F13/'05_Segment_Historical_Raw_Data'!$F7 -> 0.048860132 | E40: ='05_Segment_Historical_Raw_Data'!$F13/'05_Segment_Historical_Raw_Data'!$F7 -> 0.048860132 | F40: ='05_Segment_Historical_Raw_Data'!$F13/'05_Segment_Historical_Raw_Data'!$F7 -> 0.048860132 | G40: ='05_Segment_Historical_Raw_Data'!$F13/'05_Segment_Historical_Raw_Data'!$F7 -> 0.048860132
A41: ├── Bear Case Scenario | B41: % | C41: =C40-1% -> 0.038860132 | D41: =D40-1% -> 0.038860132 | E41: =E40-1% -> 0.038860132 | F41: =F40-1% -> 0.038860132 | G41: =G40-1% -> 0.038860132
A43: Digital Services (Jio)
A44: Revenue Growth | B44: % | C44: =(1+C57)*(1+C61) -1 -> 0.14173925 | D44: =(1+D57)*(1+D61) -1 -> 0.12578927 | E44: =(1+E57)*(1+E61) -1 -> 0.10993928 | F44: =(1+F57)*(1+F61) -1 -> 0.094189298 | G44: =(1+G57)*(1+G61) -1 -> 0.078539313 | I44: Subscriber base is approaching maturity; future growth driven mainly by ARPU increases, enterprise services, and 5G monetisation rather than rapid subscriber additions
A45: EBITDA Margin (Active) | B45: % | C45: =CHOOSE($D$2,C46,C47,C48) -> 0.4966 | D45: =CHOOSE($D$2,D46,D47,D48) -> 0.5016 | E45: =CHOOSE($D$2,E46,E47,E48) -> 0.5066 | F45: =CHOOSE($D$2,F46,F47,F48) -> 0.5116 | G45: =CHOOSE($D$2,G46,G47,G48) -> 0.5166 | I45: Operating leverage from network utilisation, 5G monetisation, and higher data consumption
A46: ├── Bull Case Scenario | B46: % | C46: =C47+2% -> 0.5166 | D46: =D47+2% -> 0.5216 | E46: =E47+2% -> 0.5266 | F46: =F47+2% -> 0.5316 | G46: =G47+2% -> 0.5366
A47: ├── Base Case Scenario | B47: % | C47: =AVERAGE('05_Segment_Historical_Raw_Data'!B25:F25) -> 0.4966 | D47: =C47+0.5% -> 0.5016 | E47: =D47+0.5% -> 0.5066 | F47: =E47+0.5% -> 0.5116 | G47: =F47+0.5% -> 0.5166
A48: ├── Bear Case Scenario | B48: % | C48: =C47-2% -> 0.4766 | D48: =D47-2% -> 0.4816 | E48: =E47-2% -> 0.4866 | F48: =F47-2% -> 0.4916 | G48: =G47-2% -> 0.4966
A49: Active Jio Multiple | B49: x | C49: =CHOOSE($D$2,C50,C51,C52) -> 15 | D49: =CHOOSE($D$2,D50,D51,D52) -> 15 | E49: =CHOOSE($D$2,E50,E51,E52) -> 15 | F49: =CHOOSE($D$2,F50,F51,F52) -> 15 | G49: =CHOOSE($D$2,G50,G51,G52) -> 15 | I49: Premium to Bharti Airtel's observed multiple, reflecting Jio's strong subscriber growth, high EBITDA margins,
A50: ├── Bull Case Scenario | B50: x | C50: =C51+2 -> 17 | D50: =D51+2 -> 17 | E50: =E51+2 -> 17 | F50: =F51+2 -> 17 | G50: =G51+2 -> 17 | I50: digital ecosystem optionality and long-term monetisation potential. The premium recognises Jio's growth
A51: ├── Base Case Scenario | B51: x | C51: 15 | D51: 15 | E51: 15 | F51: 15 | G51: 15 | I51: and strategic positioning while remaining below high-growth standalone technology/platform valuations.
A52: ├── Bear Case Scenario | B52: x | C52: =C51-2 -> 13 | D52: =D51-2 -> 13 | E52: =E51-2 -> 13 | F52: =F51-2 -> 13 | G52: =G51-2 -> 13
A53: CAPEX / Revenue (Active) | B53: % | C53: =CHOOSE($D$2,C54,C55,C56) -> 0.17881065 | D53: =CHOOSE($D$2,D54,D55,D56) -> 0.16881065 | E53: =CHOOSE($D$2,E54,E55,E56) -> 0.15881065 | F53: =CHOOSE($D$2,F54,F55,F56) -> 0.14881065 | G53: =CHOOSE($D$2,G54,G55,G56) -> 0.13881065 | I53: Peak 5G rollout phase completed; future spending shifts from expansion to maintenance
A54: ├── Bull Case Scenario | B54: % | C54: =C55-2% -> 0.15881065 | D54: =D55-2% -> 0.14881065 | E54: =E55-2% -> 0.13881065 | F54: =F55-2% -> 0.12881065 | G54: =G55-2% -> 0.11881065
A55: ├── Base Case Scenario | B55: % | C55: ='05_Segment_Historical_Raw_Data'!F28/'05_Segment_Historical_Raw_Data'!F21 -> 0.17881065 | D55: =C55-1% -> 0.16881065 | E55: =D55-1% -> 0.15881065 | F55: =E55-1% -> 0.14881065 | G55: =F55-1% -> 0.13881065
A56: ├── Bear Case Scenario | B56: % | C56: =C55+2% -> 0.19881065 | D56: =D55+2% -> 0.18881065 | E56: =E55+2% -> 0.17881065 | F56: =F55+2% -> 0.16881065 | G56: =G55+2% -> 0.15881065
A57: Subscriber Growth (Active) | B57: % | C57: =CHOOSE($D$2,C58,C59,C60) -> 0.074149939 | D57: =CHOOSE($D$2,D58,D59,D60) -> 0.064149939 | E57: =CHOOSE($D$2,E58,E59,E60) -> 0.054149939 | F57: =CHOOSE($D$2,F58,F59,F60) -> 0.044149939 | G57: =CHOOSE($D$2,G58,G59,G60) -> 0.034149939 | I57: India's telecom market is mature; incremental subscriber additions moderate as penetration increases
A58: ├── Bull Case Scenario | B58: % | C58: =C59+2% -> 0.094149939 | D58: =D59+2% -> 0.084149939 | E58: =E59+2% -> 0.074149939 | F58: =F59+2% -> 0.064149939 | G58: =G59+2% -> 0.054149939
A59: ├── Base Case Scenario | B59: % | C59: ='05_Segment_Historical_Raw_Data'!F30/'05_Segment_Historical_Raw_Data'!E30-1 -> 0.074149939 | D59: =C59-1% -> 0.064149939 | E59: =D59-1% -> 0.054149939 | F59: =E59-1% -> 0.044149939 | G59: =F59-1% -> 0.034149939
A60: ├── Bear Case Scenario | B60: % | C60: =C59-2% -> 0.054149939 | D60: =D59-2% -> 0.044149939 | E60: =E59-2% -> 0.034149939 | F60: =F59-2% -> 0.024149939 | G60: =G59-2% -> 0.014149939
A61: ARPU Growth (Active) | B61: % | C61: =CHOOSE($D$2,C62,C63,C64) -> 0.062923538 | D61: =CHOOSE($D$2,D62,D63,D64) -> 0.057923538 | E61: =CHOOSE($D$2,E62,E63,E64) -> 0.052923538 | F61: =CHOOSE($D$2,F62,F63,F64) -> 0.047923538 | G61: =CHOOSE($D$2,G62,G63,G64) -> 0.042923538 | I61: Tariff hikes expected but normalize after recent price increases
A62: ├── Bull Case Scenario | B62: % | C62: =C63+2% -> 0.082923538 | D62: =D63+2% -> 0.077923538 | E62: =E63+2% -> 0.072923538 | F62: =F63+2% -> 0.067923538 | G62: =G63+2% -> 0.062923538
A63: ├── Base Case Scenario | B63: % | C63: =AVERAGE('05_Segment_Historical_Raw_Data'!F31/'05_Segment_Historical_Raw_Data'!C31)^(1/3)-1 -> 0.062923538 | D63: =C63-0.5% -> 0.057923538 | E63: =D63-0.5% -> 0.052923538 | F63: =E63-0.5% -> 0.047923538 | G63: =F63-0.5% -> 0.042923538
A64: ├── Bear Case Scenario | B64: % | C64: =C63-2% -> 0.042923538 | D64: =D63-2% -> 0.037923538 | E64: =E63-2% -> 0.032923538 | F64: =F63-2% -> 0.027923538 | G64: =G63-2% -> 0.022923538
A66: Reliance Retail
A67: Revenue Growth (Active) | B67: % | C67: =CHOOSE($D$2,C68,C69,C70) -> 0.13404572 | D67: =CHOOSE($D$2,D68,D69,D70) -> 0.12404572 | E67: =CHOOSE($D$2,E68,E69,E70) -> 0.11404572 | F67: =CHOOSE($D$2,F68,F69,F70) -> 0.10404572 | G67: =CHOOSE($D$2,G68,G69,G70) -> 0.094045716 | I67: Store expansion + rising consumption; gradual moderation as base increases
A68: ├── Bull Case Scenario | B68: % | C68: =C69+2% -> 0.15404572 | D68: =D69+2% -> 0.14404572 | E68: =E69+2% -> 0.13404572 | F68: =F69+2% -> 0.12404572 | G68: =G69+2% -> 0.11404572
A69: ├── Base Case Scenario | B69: % | C69: =('05_Segment_Historical_Raw_Data'!F36/'05_Segment_Historical_Raw_Data'!B36)^(1/5)-1 -> 0.13404572 | D69: =C69-1% -> 0.12404572 | E69: =D69-1% -> 0.11404572 | F69: =E69-1% -> 0.10404572 | G69: =F69-1% -> 0.094045716
A70: ├── Bear Case Scenario | B70: % | C70: =C69-2% -> 0.11404572 | D70: =D69-2% -> 0.10404572 | E70: =E69-2% -> 0.094045716 | F70: =F69-2% -> 0.084045716 | G70: =G69-2% -> 0.074045716
A71: EBITDA Margin (Active) | B71: % | C71: =CHOOSE($D$2,C72,C73,C74) -> 0.080270473 | D71: =CHOOSE($D$2,D72,D73,D74) -> 0.085270473 | E71: =CHOOSE($D$2,E72,E73,E74) -> 0.090270473 | F71: =CHOOSE($D$2,F72,F73,F74) -> 0.095270473 | G71: =CHOOSE($D$2,G72,G73,G74) -> 0.10027047 | I71: Operating leverage from scale and supply-chain efficiencies
A72: ├── Bull Case Scenario | B72: % | C72: =C73+1.5% -> 0.095270473 | D72: =D73+1.5% -> 0.10027047 | E72: =E73+1.5% -> 0.10527047 | F72: =F73+1.5% -> 0.11027047 | G72: =G73+1.5% -> 0.11527047
A73: ├── Base Case Scenario | B73: % | C73: =AVERAGE('05_Segment_Historical_Raw_Data'!B38:F38) -> 0.080270473 | D73: =C73+0.5% -> 0.085270473 | E73: =D73+0.5% -> 0.090270473 | F73: =E73+0.5% -> 0.095270473 | G73: =F73+0.5% -> 0.10027047
A74: ├── Bear Case Scenario | B74: % | C74: =C73-1.5% -> 0.065270473 | D74: =D73-1.5% -> 0.070270473 | E74: =E73-1.5% -> 0.075270473 | F74: =F73-1.5% -> 0.080270473 | G74: =G73-1.5% -> 0.085270473
A75: Active Retail Multiple | B75: x | C75: =CHOOSE($D$2,C76,C77,C78) -> 22 | D75: =CHOOSE($D$2,D76,D77,D78) -> 22 | E75: =CHOOSE($D$2,E76,E77,E78) -> 22 | F75: =CHOOSE($D$2,F76,F77,F78) -> 22 | G75: =CHOOSE($D$2,G76,G77,G78) -> 22 | I75: Modest premium to the normalized peer reference multiple, supported by Reliance Retail's scale, diversified retail
A76: ├── Bull Case Scenario | B76: x | C76: =C77+4 -> 26 | D76: =D77+4 -> 26 | E76: =E77+4 -> 26 | F76: =F77+4 -> 26 | G76: =G77+4 -> 26 | I76: formats, omnichannel capabilities, slightly higher EBITDA margin than DMart in the model,and long-term formalisation
A77: ├── Base Case Scenario | B77: x | C77: 22 | D77: 22 | E77: 22 | F77: 22 | G77: 22 | I77: of India's retail market. The multiple remains materially below DMart's observed 39.86x, providing valuation discipline.
A78: ├── Bear Case Scenario | B78: x | C78: =C77-4 -> 18 | D78: =D77-4 -> 18 | E78: =E77-4 -> 18 | F78: =F77-4 -> 18 | G78: =G77-4 -> 18
A79: CAPEX / Revenue | B79: % | C79: =AVERAGE('05_Segment_Historical_Raw_Data'!F41/'05_Segment_Historical_Raw_Data'!F36,'05_Segment_Historical_Raw_Data'!E41/'05_Segment_Historical_Raw_Data'!E36,'05_Segment_Historical_Raw_Data'!D41/'05_Segment_Historical_Raw_Data'!D36) -> 0.070645664 | D79: =C79-0.5% -> 0.065645664 | E79: =D79-0.5% -> 0.060645664 | F79: =E79-0.5% -> 0.055645664 | G79: =F79-0.5% -> 0.050645664 | I79: Lower intensity after aggressive store rollout
A80: New Store Additions (Active) | B80: Count | C80: =CHOOSE($D$2,C81,C82,C83) -> 662 | D80: =CHOOSE($D$2,D81,D82,D83) -> 612 | E80: =CHOOSE($D$2,E81,E82,E83) -> 562 | F80: =CHOOSE($D$2,F81,F82,F83) -> 512 | G80: =CHOOSE($D$2,G81,G82,G83) -> 462 | I80: Expansion continues but slows as network becomes larger
A81: ├── Bull Case Scenario | B81: Count | C81: =C82+200 -> 862 | D81: =D82+200 -> 812 | E81: =E82+200 -> 762 | F81: =F82+200 -> 712 | G81: =G82+200 -> 662
A82: ├── Base Case Scenario | B82: Count | C82: =AVERAGE('05_Segment_Historical_Raw_Data'!F44-'05_Segment_Historical_Raw_Data'!E44,'05_Segment_Historical_Raw_Data'!E44-'05_Segment_Historical_Raw_Data'!D44) -> 662 | D82: =C82-50 -> 612 | E82: =D82-50 -> 562 | F82: =E82-50 -> 512 | G82: =F82-50 -> 462
A83: ├── Bear Case Scenario | B83: Count | C83: =C82-200 -> 462 | D83: =D82-200 -> 412 | E83: =E82-200 -> 362 | F83: =F82-200 -> 312 | G83: =G82-200 -> 262
A85: Oil & Gas
A86: Revenue Growth (Active) | B86: % | C86: =CHOOSE($D$2,C87,C88,C89) -> 0.076462329 | D86: =CHOOSE($D$2,D87,D88,D89) -> 0.068962329 | E86: =CHOOSE($D$2,E87,E88,E89) -> 0.061462329 | F86: =CHOOSE($D$2,F87,F88,F89) -> 0.053962329 | G86: =CHOOSE($D$2,G87,G88,G89) -> 0.046462329 | I86: Stable gas prices with gradual production decline
A87: ├── Bull Case Scenario | B87: % | C87: =+C88+1.5% -> 0.091462329 | D87: =+D88+1.5% -> 0.083962329 | E87: =+E88+1.5% -> 0.076462329 | F87: =+F88+1.5% -> 0.068962329 | G87: =+G88+1.5% -> 0.061462329
A88: ├── Base Case Scenario | B88: % | C88: =('05_Segment_Historical_Raw_Data'!F48/'05_Segment_Historical_Raw_Data'!C48)^(1/5)-1 -> 0.076462329 | D88: =C88-0.75% -> 0.068962329 | E88: =D88-0.75% -> 0.061462329 | F88: =E88-0.75% -> 0.053962329 | G88: =F88-0.75% -> 0.046462329
A89: ├── Bear Case Scenario | B89: % | C89: =C88-1.5% -> 0.061462329 | D89: =D88-1.5% -> 0.053962329 | E89: =E88-1.5% -> 0.046462329 | F89: =F88-1.5% -> 0.038962329 | G89: =G88-1.5% -> 0.031462329
A90: EBITDA Margin (Active) | B90: % | C90: =CHOOSE($D$2,C91,C92,C93) -> 0.80066759 | D90: =CHOOSE($D$2,D91,D92,D93) -> 0.79566759 | E90: =CHOOSE($D$2,E91,E92,E93) -> 0.79066759 | F90: =CHOOSE($D$2,F91,F92,F93) -> 0.78566759 | G90: =CHOOSE($D$2,G91,G92,G93) -> 0.78066759 | I90: Maintained due to low-cost upstream operations
A91: ├── Bull Case Scenario | B91: % | C91: =+C92+1.5% -> 0.81566759 | D91: =+D92+1.5% -> 0.81066759 | E91: =+E92+1.5% -> 0.80566759 | F91: =+F92+1.5% -> 0.80066759 | G91: =+G92+1.5% -> 0.79566759
A92: ├── Base Case Scenario | B92: % | C92: =AVERAGE('05_Segment_Historical_Raw_Data'!B50:F50) -> 0.80066759 | D92: =C92-0.5% -> 0.79566759 | E92: =D92-0.5% -> 0.79066759 | F92: =E92-0.5% -> 0.78566759 | G92: =F92-0.5% -> 0.78066759
A93: ├── Bear Case Scenario | B93: % | C93: =C92-1.5% -> 0.78566759 | D93: =D92-1.5% -> 0.78066759 | E93: =E92-1.5% -> 0.77566759 | F93: =F92-1.5% -> 0.77066759 | G93: =G92-1.5% -> 0.76566759
A94: Active Oil & Gas (E&P) Multiple | B94: x | C94: =CHOOSE($D$2,C95,C96,C97) -> 5.5 | D94: =CHOOSE($D$2,D95,D96,D97) -> 5.5 | E94: =CHOOSE($D$2,E95,E96,E97) -> 5.5 | F94: =CHOOSE($D$2,F95,F96,F97) -> 5.5 | G94: =CHOOSE($D$2,G95,G96,G97) -> 5.5 | I94: Premium to ONGC's observed multiple, used as a reference peer rather than a direct like-for-like benchmark due
A95: ├── Bull Case Scenario | B95: x | C95: =C96+1 -> 6.5 | D95: =D96+1 -> 6.5 | E95: =E96+1 -> 6.5 | F95: =F96+1 -> 6.5 | G95: =G96+1 -> 6.5 | I95: to differences in ownership scale, asset portfolio and capital allocation. The higher multiple reflects Reliance's
A96: ├── Base Case Scenario | B96: x | C96: 5.5 | D96: 5.5 | E96: 5.5 | F96: 5.5 | G96: 5.5 | I96: private-sector operating model, strategic E&P assets, portfolio optionality and integration within the broader energy platform.
A97: ├── Bear Case Scenario | B97: x | C97: =C96-1 -> 4.5 | D97: =D96-1 -> 4.5 | E97: =E96-1 -> 4.5 | F97: =F96-1 -> 4.5 | G97: =G96-1 -> 4.5
A98: CAPEX / Revenue | B98: % | C98: =(AVERAGE('05_Segment_Historical_Raw_Data'!F52/'05_Segment_Historical_Raw_Data'!F48,'05_Segment_Historical_Raw_Data'!E52/'05_Segment_Historical_Raw_Data'!E48,'05_Segment_Historical_Raw_Data'!D52/'05_Segment_Historical_Raw_Data'!D48))/3 -> 0.079487665 | D98: =C98-0.5% -> 0.074487665 | E98: =D98-0.5% -> 0.069487665 | F98: =E98-0.5% -> 0.064487665 | G98: =F98-0.5% -> 0.059487665 | I98: Sustaining investment for field development
A99: KG-D6 Gas Production Growth | B99: % | C99: =(1+C88)/(1+C102)-1 -> 0.055355224 | D99: =(1+D88)/(1+D102)-1 -> 0.048002283 | E99: =(1+E88)/(1+E102)-1 -> 0.040649342 | F99: =(1+F88)/(1+F102)-1 -> 0.033296401 | G99: =(1+G88)/(1+G102)-1 -> 0.02594346 | I99: Mature KG-D6 field decline profile
A100: KG-D6 Realised Gas Price Delta (Active) | B100: % | C100: =CHOOSE($D$2,C101,C102,C103) -> 0.02 | D100: =CHOOSE($D$2,D101,D102,D103) -> 0.02 | E100: =CHOOSE($D$2,E101,E102,E103) -> 0.02 | F100: =CHOOSE($D$2,F101,F102,F103) -> 0.02 | G100: =CHOOSE($D$2,G101,G102,G103) -> 0.02 | I100: Moderate inflation-linked increase
A101: ├── Bull Case Scenario | B101: % | C101: =C102+3% -> 0.05 | D101: =D102+3% -> 0.05 | E101: =E102+3% -> 0.05 | F101: =F102+3% -> 0.05 | G101: =G102+3% -> 0.05
A102: ├── Base Case Scenario | B102: % | C102: 0.02 | D102: 0.02 | E102: 0.02 | F102: 0.02 | G102: 0.02
A103: ├── Bear Case Scenario | B103: % | C103: =C102-3% -> -0.01 | D103: =D102-3% -> -0.01 | E103: =E102-3% -> -0.01 | F103: =F102-3% -> -0.01 | G103: =G102-3% -> -0.01
A105: Capital Allocation and Leverage
A106: Total Group Capital Expenditure Growth | B106: % | C106: =AVERAGE('04_Consolidated_Cash_Flow'!F8/'04_Consolidated_Cash_Flow'!E8,'04_Consolidated_Cash_Flow'!E8/'04_Consolidated_Cash_Flow'!D8,'04_Consolidated_Cash_Flow'!D8/'04_Consolidated_Cash_Flow'!C8,'04_Consolidated_Cash_Flow'!C8/'04_Consolidated_Cash_Flow'!B8)-1 -> 0.072383762 | D106: =C106*0.8 -> 0.05790701 | E106: =D106*0.8 -> 0.046325608 | F106: =E106*0.8 -> 0.037060486 | G106: =((-('09_Free_Cash_Flow_Schedule FCFF'!F11*1.25)/'08_Three_Statement_Projections'!F122-1)) -> -0.31583519 | I106: Year 1 incorporates the historical 7.24% capex growth rate to reflect near-term infrastructure commitments. Years 2 through 5 utilize a structural taper to transition the asset base into a steady-state harvesting phase.
...

Sheet 08_Three_Statement_Projections
A1: RELIANCE INDUSTRIES LIMITED
A2: THREE STATEMENT PROJECTIONS
A3: (₹ in Crore)
A5: Projected P&L
A6: Projected Line Item | B6: FY 2025-26 (Act) | C6: FY 2026-27 (Proj) | D6: FY 2027-28 (Proj) | E6: FY 2028-29 (Proj) | F6: FY 2029-30 (Proj) | G6: FY 2030-31 (Proj)
A7: SEGMENT REVENUE BUILDUP
A8: Oil-to-Chemicals (O2C) Revenue | B8: ='05_Segment_Historical_Raw_Data'!F7 -> 662401 | C8: =B8*(1+'07_Forecast_assumptions'!C21) -> 685873.44 | D8: =C8*(1+'07_Forecast_assumptions'!D21) -> 710177.64 | E8: =D8*(1+'07_Forecast_assumptions'!E21) -> 735343.07 | F8: =E8*(1+'07_Forecast_assumptions'!F21) -> 761400.24 | G8: =F8*(1+'07_Forecast_assumptions'!G21) -> 788380.76
A9: Digital Services (Jio) Revenue | B9: ='05_Segment_Historical_Raw_Data'!F22 -> 149965 | C9: =B9*(1+'07_Forecast_assumptions'!C57)*(1+'07_Forecast_assumptions'!C61) -> 171220.93 | D9: =C9*(1+'07_Forecast_assumptions'!D57)*(1+'07_Forecast_assumptions'!D61) -> 192758.68 | E9: =D9*(1+'07_Forecast_assumptions'!E57)*(1+'07_Forecast_assumptions'!E61) -> 213950.43 | F9: =E9*(1+'07_Forecast_assumptions'!F57)*(1+'07_Forecast_assumptions'!F61) -> 234102.27 | G9: =F9*(1+'07_Forecast_assumptions'!G57)*(1+'07_Forecast_assumptions'!G61) -> 252488.51
A10: Organised Retail Revenue | B10: ='05_Segment_Historical_Raw_Data'!F36 -> 328202 | C10: =B10*(1+'07_Forecast_assumptions'!C67) -> 372196.07 | D10: =C10*(1+'07_Forecast_assumptions'!D67) -> 418365.4 | E10: =D10*(1+'07_Forecast_assumptions'!E67) -> 466078.18 | F10: =E10*(1+'07_Forecast_assumptions'!F67) -> 514571.62 | G10: =F10*(1+'07_Forecast_assumptions'!G67) -> 562964.88
A11: Oil & Gas (E&P) Revenue | B11: ='05_Segment_Historical_Raw_Data'!F48 -> 23861 | C11: =B11*(1+'07_Forecast_assumptions'!C86) -> 25685.468 | D11: =C11*(1+'07_Forecast_assumptions'!D86) -> 27456.797 | E11: =D11*(1+'07_Forecast_assumptions'!E86) -> 29144.356 | F11: =E11*(1+'07_Forecast_assumptions'!F86) -> 30717.053 | G11: =F11*(1+'07_Forecast_assumptions'!G86) -> 32144.239
A12: Other Operations & Adjustments | B12: ='02_Consolidated_Historical_Data'!F6-SUM('08_Three_Statement_Projections'!B8:B11) -> 11490 | C12: =B12*(1+'06_Calculated_Ratios'!$F$5) -> 12609.991 | D12: =C12*(1+'06_Calculated_Ratios'!$F$5) -> 13839.153 | E12: =D12*(1+'06_Calculated_Ratios'!$F$5) -> 15188.127 | F12: =E12*(1+'06_Calculated_Ratios'!$F$5) -> 16668.594 | G12: =F12*(1+'06_Calculated_Ratios'!$F$5) -> 18293.369
A14: Total Revenue | B14: =+SUM(B8:B12) -> 1175919 | C14: =+SUM(C8:C12) -> 1267585.9 | D14: =+SUM(D8:D12) -> 1362597.7 | E14: =+SUM(E8:E12) -> 1459704.2 | F14: =+SUM(F8:F12) -> 1557459.8 | G14: =+SUM(G8:G12) -> 1654271.7
A16: SEGMENT EBITDA BUILDUP
A17: Oil-to-Chemicals (O2C) EBITDA | B17: ='05_Segment_Historical_Raw_Data'!F9 -> 60546 | C17: ='08_Three_Statement_Projections'!C8*'07_Forecast_assumptions'!C27 -> 66526.374 | D17: ='08_Three_Statement_Projections'!D8*'07_Forecast_assumptions'!D27 -> 68883.762 | E17: ='08_Three_Statement_Projections'!E8*'07_Forecast_assumptions'!E27 -> 71324.685 | F17: ='08_Three_Statement_Projections'!F8*'07_Forecast_assumptions'!F27 -> 73852.104 | G17: ='08_Three_Statement_Projections'!G8*'07_Forecast_assumptions'!G27 -> 76469.082
A18: Digital Services (Jio) EBITDA | B18: ='05_Segment_Historical_Raw_Data'!F24 -> 76560 | C18: =C9*'07_Forecast_assumptions'!C47 -> 85028.312 | D18: =D9*'07_Forecast_assumptions'!D47 -> 96687.755 | E18: =E9*'07_Forecast_assumptions'!E47 -> 108387.29 | F18: =F9*'07_Forecast_assumptions'!F47 -> 119766.72 | G18: =G9*'07_Forecast_assumptions'!G47 -> 130435.56
A19: Organised Retail EBITDA | B19: ='05_Segment_Historical_Raw_Data'!F37 -> 27034 | C19: =C10*'07_Forecast_assumptions'!C71 -> 29876.355 | D19: =D10*'07_Forecast_assumptions'!D71 -> 35674.216 | E19: =E10*'07_Forecast_assumptions'!E71 -> 42073.098 | F19: =F10*'07_Forecast_assumptions'!F71 -> 49023.482 | G19: =G10*'07_Forecast_assumptions'!G71 -> 56448.755
A20: Oil & Gas (E&P) EBITDA | B20: ='05_Segment_Historical_Raw_Data'!F49 -> 19050 | C20: =C11*'07_Forecast_assumptions'!C90 -> 20565.521 | D20: =D11*'07_Forecast_assumptions'!D90 -> 21846.484 | E20: =E11*'07_Forecast_assumptions'!E90 -> 23043.498 | F20: =F11*'07_Forecast_assumptions'!F90 -> 24133.393 | G20: =G11*'07_Forecast_assumptions'!G90 -> 25093.966
A21: Other Operations & Adjustments EBITDA | B21: ='02_Consolidated_Historical_Data'!F16-SUM('08_Three_Statement_Projections'!B17:B20) -> 24721 | C21: =B21*(1+'06_Calculated_Ratios'!$F$6) -> 28021.545 | D21: =C21*(1+'06_Calculated_Ratios'!$F$6) -> 31762.752 | E21: =D21*(1+'06_Calculated_Ratios'!$F$6) -> 36003.454 | F21: =E21*(1+'06_Calculated_Ratios'!$F$6) -> 40810.339 | G21: =F21*(1+'06_Calculated_Ratios'!$F$6) -> 46259.001
A23: Total EBITDA | B23: =+SUM(B16:B21) -> 207911 | C23: =+SUM(C16:C21) -> 230018.11 | D23: =+SUM(D16:D21) -> 254854.97 | E23: =+SUM(E16:E21) -> 280832.02 | F23: =+SUM(F16:F21) -> 307586.04 | G23: =+SUM(G16:G21) -> 334706.37
A25: GROUP P&L ROLLUP
A26: Consolidated Group EBITDA | B26: =B23 -> 207911 | C26: =C23 -> 230018.11 | D26: =D23 -> 254854.97 | E26: =E23 -> 280832.02 | F26: =F23 -> 307586.04 | G26: =G23 -> 334706.37
A27: (-) Depreciation & Amortisation | B27: ='02_Consolidated_Historical_Data'!F17 -> 57688 | C27: =B27*(1+0.075) -> 62014.6 | D27: =C27*(1+0.075) -> 66665.695 | E27: =D27*(1+0.075) -> 71665.622 | F27: =E27*(1+0.075) -> 77040.544 | G27: =F27*(1+0.075) -> 82818.585
A28: Consolidated EBIT | B28: =B26-B27 -> 150223 | C28: =C26-C27 -> 168003.51 | D28: =D26-D27 -> 188189.27 | E28: =E26-E27 -> 209166.4 | F28: =F26-F27 -> 230545.5 | G28: =G26-G27 -> 251887.78
A29: (-) Finance Cost (Interest Expense) | B29: =-'02_Consolidated_Historical_Data'!F19 -> -27061 | C29: =B29*(1+'07_Forecast_assumptions'!C107) -> -29694.259 | D29: =C29*(1+'07_Forecast_assumptions'!D107) -> -32583.755 | E29: =D29*(1+'07_Forecast_assumptions'!E107) -> -35754.423 | F29: =E29*(1+'07_Forecast_assumptions'!F107) -> -39233.624 | G29: =F29*(1+'07_Forecast_assumptions'!G107) -> -43051.379
A30: (+) Other Income | B30: 19252 | C30: =B30*(1+5%) -> 20214.6 | D30: =C30*(1+5%) -> 21225.33 | E30: =D30*(1+5%) -> 22286.597 | F30: =E30*(1+5%) -> 23400.926 | G30: =F30*(1+5%) -> 24570.973
A32: Profit Before Tax (PBT) | B32: =B28+B29+B30 -> 142414 | C32: =C28+C29+C30 -> 158523.85 | D32: =D28+D29+D30 -> 176830.85 | E32: =E28+E29+E30 -> 195698.58 | F32: =F28+F29+F30 -> 214712.8 | G32: =G28+G29+G30 -> 233407.37
A34: (-) Tax Expense | B34: -27552 | C34: =-C32*'07_Forecast_assumptions'!C6/100 -> -39900.453 | D34: =-D32*'07_Forecast_assumptions'!D6/100 -> -44508.324 | E34: =-E32*'07_Forecast_assumptions'!E6/100 -> -49257.331 | F34: =-F32*'07_Forecast_assumptions'!F6/100 -> -54043.212 | G34: =-G32*'07_Forecast_assumptions'!G6/100 -> -58748.636
A36: Profit After Tax (PAT) | B36: =B32+B34 -> 114862 | C36: =C32+C34 -> 118623.4 | D36: =D32+D34 -> 132322.52 | E36: =E32+E34 -> 146441.24 | F36: =F32+F34 -> 160669.59 | G36: =G32+G34 -> 174658.74
A38: (-) Non-Controlling Interest (NCI) | B38: =-'02_Consolidated_Historical_Data'!F25 -> -20108 | C38: =-C36* 18% -> -21352.211 | D38: =-D36* 18% -> -23818.054 | E38: =-E36* 18% -> -26359.424 | F38: =-F36* 18% -> -28920.526 | G38: =-G36* 18% -> -31438.573
A39: ='02_Consolidated_Historical_Data'!A24 -> Share of Profit/(Loss) of JVs & Associates | B39: ='02_Consolidated_Historical_Data'!F24 -> 1000 | C39: =B39*1.1 -> 1100 | D39: =C39*1.1 -> 1210 | E39: =D39*1.1 -> 1331 | F39: =E39*1.1 -> 1464.1 | G39: =F39*1.1 -> 1610.51
A41: PAT Final (Attributable to Owners) | B41: =B36+B38+B39 -> 95754 | C41: =C36+C38+C39 -> 98371.185 | D41: =D36+D38+D39 -> 109714.47 | E41: =E36+E38+E39 -> 121412.82 | F41: =F36+F38+F39 -> 133213.16 | G41: =G36+G38+G39 -> 144830.68
A44: Projected Balance Sheet
A45: Projected Line Item | B45: FY 2025-26 (Act) | C45: FY 2026-27 (Proj) | D45: FY 2027-28 (Proj) | E45: FY 2028-29 (Proj) | F45: FY 2029-30 (Proj) | G45: FY 2030-31 (Proj)
A46: ASSETS NON-CURRENT
A47: Property, Plant and Equipment | B47: ='08A_Balance_Sheet_Support_Sched'!C8 -> 751087 | C47: ='08A_Balance_Sheet_Support_Sched'!D8 -> 820885.52 | D47: ='08A_Balance_Sheet_Support_Sched'!E8 -> 893666.33 | E47: ='08A_Balance_Sheet_Support_Sched'!F8 -> 968825.33 | F47: ='08A_Balance_Sheet_Support_Sched'!G8 -> 1045612.7 | G47: ='08A_Balance_Sheet_Support_Sched'!H8 -> 1070828.6
A48: Capital Work in Progress | B48: ='03_Consolidated_Balance_Sheet_'!F9 -> 192287 | C48: =B48*95% -> 182672.65 | D48: =C48*95% -> 173539.02 | E48: =D48*95% -> 164862.07 | F48: =E48*95% -> 156618.96 | G48: =F48*95% -> 148788.02
A49: Spectrum & Related Assets | B49: ='03_Consolidated_Balance_Sheet_'!F10 -> 196731 | C49: =B49 -> 196731 | D49: =C49 -> 196731 | E49: =D49 -> 196731 | F49: =E49 -> 196731 | G49: =F49 -> 196731
A50: Goodwill & Intangible Assets | B50: ='03_Consolidated_Balance_Sheet_'!F11 -> 222376 | C50: =B50 -> 222376 | D50: =C50 -> 222376 | E50: =D50 -> 222376 | F50: =E50 -> 222376 | G50: =F50 -> 222376
A51: Non-Current Investments | B51: ='03_Consolidated_Balance_Sheet_'!F12 -> 150901 | C51: =B51 -> 150901 | D51: =C51 -> 150901 | E51: =D51 -> 150901 | F51: =E51 -> 150901 | G51: =F51 -> 150901
A52: Loans & Other Financial Assets | B52: ='03_Consolidated_Balance_Sheet_'!F13 -> 5725 | C52: =B52 -> 5725 | D52: =C52 -> 5725 | E52: =D52 -> 5725 | F52: =E52 -> 5725 | G52: =F52 -> 5725
A53: ='03_Consolidated_Balance_Sheet_'!A14 -> Deferred Tax Assets (Net) ₹ Crore | B53: ='03_Consolidated_Balance_Sheet_'!F14 -> 594 | C53: =B53 -> 594 | D53: =C53 -> 594 | E53: =D53 -> 594 | F53: =E53 -> 594 | G53: =F53 -> 594
A54: ='03_Consolidated_Balance_Sheet_'!A15 -> Other Non-Current Assets ₹ Crore | B54: ='03_Consolidated_Balance_Sheet_'!F15 -> 64190 | C54: =B54 -> 64190 | D54: =C54 -> 64190 | E54: =D54 -> 64190 | F54: =E54 -> 64190 | G54: =F54 -> 64190
A56: Total Non-Current Assets | B56: =SUM(B47:B54) -> 1583891 | C56: =SUM(C47:C54) -> 1644075.2 | D56: =SUM(D47:D54) -> 1707722.3 | E56: =SUM(E47:E54) -> 1774204.4 | F56: =SUM(F47:F54) -> 1842748.7 | G56: =SUM(G47:G54) -> 1860133.7
A58: ASSETS CURRENT
A59: Inventories | B59: ='08A_Balance_Sheet_Support_Sched'!C11 -> 166941 | C59: ='08A_Balance_Sheet_Support_Sched'!D11 -> 179997.2 | D59: ='08A_Balance_Sheet_Support_Sched'!E11 -> 193488.87 | E59: ='08A_Balance_Sheet_Support_Sched'!F11 -> 207277.99 | F59: ='08A_Balance_Sheet_Support_Sched'!G11 -> 221159.29 | G59: ='08A_Balance_Sheet_Support_Sched'!H11 -> 234906.59
A60: ='03_Consolidated_Balance_Sheet_'!A20 -> Current Investments ₹ Crore | B60: ='03_Consolidated_Balance_Sheet_'!F20 -> 97431 | C60: =B60 -> 97431 | D60: =C60 -> 97431 | E60: =D60 -> 97431 | F60: =E60 -> 97431 | G60: =F60 -> 97431
A61: ='03_Consolidated_Balance_Sheet_'!A21 -> Trade Receivables ₹ Crore | B61: ='08A_Balance_Sheet_Support_Sched'!C12 -> 58491 | C61: ='08A_Balance_Sheet_Support_Sched'!D12 -> 63379.295 | D61: ='08A_Balance_Sheet_Support_Sched'!E12 -> 68129.884 | E61: ='08A_Balance_Sheet_Support_Sched'!F12 -> 72985.208 | F61: ='08A_Balance_Sheet_Support_Sched'!G12 -> 77872.989 | G61: ='08A_Balance_Sheet_Support_Sched'!H12 -> 82713.587
A62: ='03_Consolidated_Balance_Sheet_'!A22 -> Cash & Cash Equivalents ₹ Crore | B62: ='03_Consolidated_Balance_Sheet_'!F22 -> 145977 | C62: =C139 -> 155350.17 | D62: =D139 -> 178251.1 | E62: =E139 -> 216005.59 | F62: =F139 -> 270008.06 | G62: =G139 -> 393507.33
A63: Current Loans & Other Financial asset | B63: ='03_Consolidated_Balance_Sheet_'!F23 -> 62796 | C63: =B63 -> 62796 | D63: =C63 -> 62796 | E63: =D63 -> 62796 | F63: =E63 -> 62796 | G63: =F63 -> 62796
A64: Other Current Assets | B64: ='03_Consolidated_Balance_Sheet_'!F24 -> 62613 | C64: =B64 -> 62613 | D64: =C64 -> 62613 | E64: =D64 -> 62613 | F64: =E64 -> 62613 | G64: =F64 -> 62613
A66: Total Current Assets | B66: =SUM(B59:B64) -> 594249 | C66: =SUM(C59:C64) -> 621566.66 | D66: =SUM(D59:D64) -> 662709.85 | E66: =SUM(E59:E64) -> 719108.79 | F66: =SUM(F59:F64) -> 791880.34 | G66: =SUM(G59:G64) -> 933967.51
A67: Other Assets Adjustment | B67: =B99-B69 -> 0 | C67: =C99-C69 -> -7487.4013 | D67: =D99-D69 -> -16975.199 | E67: =E99-E69 -> -29368.371 | F67: =F99-F69 -> -45272.914 | G67: =G99-G69 -> -64951.127 | I67: Balancing adjustment reflects unmodelled consolidation items and other comprehensive income movements. Forecast impact is immaterial (<0.5% of total assets).
A69: Total Assets (Before Adjustments) | B69: =B56+B66 -> 2178140 | C69: =C56+C66 -> 2265641.8 | D69: =D56+D66 -> 2370432.2 | E69: =E56+E66 -> 2493313.2 | F69: =F56+F66 -> 2634629.1 | G69: =G56+G66 -> 2794101.2
A71: EQUITY
A72: Equity Share Capital | B72: ='03_Consolidated_Balance_Sheet_'!N8 -> 13532 | C72: =B72 -> 13532 | D72: =C72 -> 13532 | E72: =D72 -> 13532 | F72: =E72 -> 13532 | G72: =F72 -> 13532
A73: Other Equity | B73: ='03_Consolidated_Balance_Sheet_'!N9 -> 890498 | C73: =B73+C41-7443 -> 981426.18 | D73: =C73+D41-7443 -> 1083697.7 | E73: =D73+E41-7443 -> 1197667.5 | F73: =E73+F41-7443 -> 1323437.6 | G73: =F73+G41-7443 -> 1460825.3
A74: Non-Controlling Interest | B74: ='08A_Balance_Sheet_Support_Sched'!C19 -> 181836 | C74: =B74 -> 181836 | D74: =C74 -> 181836 | E74: =D74 -> 181836 | F74: =E74 -> 181836 | G74: =F74 -> 181836
A76: Total Equity | B76: =SUM(B72:B74) -> 1085866 | C76: =SUM(C72:C74) -> 1176794.2 | D76: =SUM(D72:D74) -> 1279065.7 | E76: =SUM(E72:E74) -> 1393035.5 | F76: =SUM(F72:F74) -> 1518805.6 | G76: =SUM(G72:G74) -> 1656193.3
A78: NON-CURRENT LIABILITIES
A79: Long-term Borrowings | B79: ='03_Consolidated_Balance_Sheet_'!N14 -> 270751 | C79: =B79*(1-'07_Forecast_assumptions'!C107) -> 244404.69 | D79: =C79*(1-'07_Forecast_assumptions'!D107) -> 220622.1 | E79: =D79*(1-'07_Forecast_assumptions'!E107) -> 199153.75 | F79: =E79*(1-'07_Forecast_assumptions'!F107) -> 179774.44 | G79: =F79*(1-'07_Forecast_assumptions'!G107) -> 162280.91
A80: Lease Liabilities | B80: ='03_Consolidated_Balance_Sheet_'!N15 -> 16198 | C80: =B80 -> 16198 | D80: =C80 -> 16198 | E80: =D80 -> 16198 | F80: =E80 -> 16198 | G80: =F80 -> 16198
A81: Deferred Payment Liabilities | B81: ='03_Consolidated_Balance_Sheet_'!N16 -> 99552 | C81: =B81-10000 -> 89552 | D81: =C81-10000 -> 79552 | E81: =D81-10000 -> 69552 | F81: =E81-10000 -> 59552 | G81: =F81-10000 -> 49552
A82: Deferred Tax Liabilities (Net) | B82: ='03_Consolidated_Balance_Sheet_'!N17 -> 97961 | C82: =B82 -> 97961 | D82: =C82 -> 97961 | E82: =D82 -> 97961 | F82: =E82 -> 97961 | G82: =F82 -> 97961
A83: Other Non-Current Liabilities | B83: ='03_Consolidated_Balance_Sheet_'!N18 -> 66558 | C83: =B83 -> 66558 | D83: =C83 -> 66558 | E83: =D83 -> 66558 | F83: =E83 -> 66558 | G83: =F83 -> 66558
A85: Total Non-Current Liabilities | B85: =SUM(B79:B83) -> 551020 | C85: =SUM(C79:C83) -> 514673.69 | D85: =SUM(D79:D83) -> 480891.1 | E85: =SUM(E79:E83) -> 449422.75 | F85: =SUM(F79:F83) -> 420043.44 | G85: =SUM(G79:G83) -> 392549.91
A87: CURRENT LIABILITIES
A88: Short-term Borrowings | B88: ='03_Consolidated_Balance_Sheet_'!N22 -> 103670 | C88: =B88 -> 103670 | D88: =C88 -> 103670 | E88: =D88 -> 103670 | F88: =E88 -> 103670 | G88: =F88 -> 103670
A89: Current Lease Liabilities | B89: ='03_Consolidated_Balance_Sheet_'!N23 -> 7381 | C89: =B89 -> 7381 | D89: =C89 -> 7381 | E89: =D89 -> 7381 | F89: =E89 -> 7381 | G89: =F89 -> 7381
A90: Trade Payable | B90: ='08A_Balance_Sheet_Support_Sched'!C13 -> 158842 | C90: ='08A_Balance_Sheet_Support_Sched'!D13 -> 171124.1 | D90: ='08A_Balance_Sheet_Support_Sched'!E13 -> 183950.69 | E90: ='08A_Balance_Sheet_Support_Sched'!F13 -> 197060.06 | F90: ='08A_Balance_Sheet_Support_Sched'!G13 -> 210257.07 | G90: ='08A_Balance_Sheet_Support_Sched'!H13 -> 223326.69
A91: Other Current Financial Liabilities | B91: ='03_Consolidated_Balance_Sheet_'!N25 -> 64660 | C91: =B91 -> 64660 | D91: =C91 -> 64660 | E91: =D91 -> 64660 | F91: =E91 -> 64660 | G91: =F91 -> 64660
A92: Other Current Liabilities | B92: ='03_Consolidated_Balance_Sheet_'!N26 -> 201503 | C92: =B92*(1+AVERAGE('07_Forecast_assumptions'!$G$23,'07_Forecast_assumptions'!$G$44,'07_Forecast_assumptions'!$G$69,'07_Forecast_assumptions'!$G$88)) -> 214322.76 | D92: =C92*(1+AVERAGE('07_Forecast_assumptions'!$G$23,'07_Forecast_assumptions'!$G$44,'07_Forecast_assumptions'!$G$69,'07_Forecast_assumptions'!$G$88)) -> 227958.12 | E92: =D92*(1+AVERAGE('07_Forecast_assumptions'!$G$23,'07_Forecast_assumptions'!$G$44,'07_Forecast_assumptions'!$G$69,'07_Forecast_assumptions'!$G$88)) -> 242460.97 | F92: =E92*(1+AVERAGE('07_Forecast_assumptions'!$G$23,'07_Forecast_assumptions'!$G$44,'07_Forecast_assumptions'!$G$69,'07_Forecast_assumptions'!$G$88)) -> 257886.51 | G92: =F92*(1+AVERAGE('07_Forecast_assumptions'!$G$23,'07_Forecast_assumptions'!$G$44,'07_Forecast_assumptions'!$G$69,'07_Forecast_assumptions'!$G$88)) -> 274293.42
A93: Other Current Provisions | B93: ='03_Consolidated_Balance_Sheet_'!N27 -> 5198 | C93: =B93*(1+AVERAGE('07_Forecast_assumptions'!$G$23,'07_Forecast_assumptions'!$G$44,'07_Forecast_assumptions'!$G$69,'07_Forecast_assumptions'!$G$88)) -> 5528.7003 | D93: =C93*(1+AVERAGE('07_Forecast_assumptions'!$G$23,'07_Forecast_assumptions'!$G$44,'07_Forecast_assumptions'!$G$69,'07_Forecast_assumptions'!$G$88)) -> 5880.4401 | E93: =D93*(1+AVERAGE('07_Forecast_assumptions'!$G$23,'07_Forecast_assumptions'!$G$44,'07_Forecast_assumptions'!$G$69,'07_Forecast_assumptions'!$G$88)) -> 6254.5577 | F93: =E93*(1+AVERAGE('07_Forecast_assumptions'!$G$23,'07_Forecast_assumptions'!$G$44,'07_Forecast_assumptions'!$G$69,'07_Forecast_assumptions'!$G$88)) -> 6652.477 | G93: =F93*(1+AVERAGE('07_Forecast_assumptions'!$G$23,'07_Forecast_assumptions'!$G$44,'07_Forecast_assumptions'!$G$69,'07_Forecast_assumptions'!$G$88)) -> 7075.7121
A95: Total Current Liabilities | B95: =SUM(B88:B93) -> 541254 | C95: =SUM(C88:C93) -> 566686.56 | D95: =SUM(D88:D93) -> 593500.25 | E95: =SUM(E88:E93) -> 621486.59 | F95: =SUM(F88:F93) -> 650507.06 | G95: =SUM(G88:G93) -> 680406.82
A97: Total Liabilities | B97: =B85+B95 -> 1092274 | C97: =C85+C95 -> 1081360.2 | D97: =D85+D95 -> 1074391.3 | E97: =E85+E95 -> 1070909.3 | F97: =F85+F95 -> 1070550.5 | G97: =G85+G95 -> 1072956.7
A99: Total Equities & Liabilities | B99: =B97+B76 -> 2178140 | C99: =C97+C76 -> 2258154.4 | D99: =D97+D76 -> 2353457 | E99: =E97+E76 -> 2463944.8 | F99: =F97+F76 -> 2589356.1 | G99: =G97+G76 -> 2729150
A101: Check (Total Equity & Liabilities - Adjusted total assets) | B101: =B99-B69-B67 -> 0 | C101: =C99-C69-C67 -> 0 | D101: =D99-D69-D67 -> 0 | E101: =E99-E69-E67 -> 0 | F101: =F99-F69-F67 -> 0 | G101: =G99-G69-G67 -> 0
A103: Projected Cash Flow Statement
A104: Projected Line Item | B104: FY 2025-26 (Act) | C104: FY 2026-27 (Proj) | D104: FY 2027-28 (Proj) | E104: FY 2028-29 (Proj) | F104: FY 2029-30 (Proj) | G104: FY 2030-31 (Proj)
A105: CASH FLOW FROM OPERATING ACTIVITIES
A106: Net Profit Before Tax (PBT) | B106: =B32 -> 142414 | C106: =C32 -> 158523.85 | D106: =D32 -> 176830.85 | E106: =E32 -> 195698.58 | F106: =F32 -> 214712.8 | G106: =G32 -> 233407.37
A107: (+) Depreciation & Amortisation | B107: =B27 -> 57688 | C107: =C27 -> 62014.6 | D107: =D27 -> 66665.695 | E107: =E27 -> 71665.622 | F107: =F27 -> 77040.544 | G107: =G27 -> 82818.585
A108: (+) Finance Costs | B108: =-B29 -> 27061 | C108: =-C29 -> 29694.259 | D108: =-D29 -> 32583.755 | E108: =-E29 -> 35754.423 | F108: =-F29 -> 39233.624 | G108: =-G29 -> 43051.379
A109: (-) Tax Paid | B109: =B34 -> -27552 | C109: =C34 -> -39900.453 | D109: =D34 -> -44508.324 | E109: =E34 -> -49257.331 | F109: =F34 -> -54043.212 | G109: =G34 -> -58748.636
A111: Operating Profit Before Working Capital Changes | B111: =SUM(B106:B109) -> 199611 | C111: =SUM(C106:C109) -> 210332.25 | D111: =SUM(D106:D109) -> 231571.97 | E111: =SUM(E106:E109) -> 253861.29 | F111: =SUM(F106:F109) -> 276943.76 | G111: =SUM(G106:G109) -> 300528.7
A113: WORKING CAPITAL ADJUSTMENT
A114: =A111 -> Operating Profit Before Working Capital Changes | B114: =B111 -> 199611 | C114: =C111 -> 210332.25 | D114: =D111 -> 231571.97 | E114: =E111 -> 253861.29 | F114: =F111 -> 276943.76 | G114: =G111 -> 300528.7
A115: (-/+) Increase / Decrease in Inventories | B115: =-('03_Consolidated_Balance_Sheet_'!F19-'03_Consolidated_Balance_Sheet_'!E19) -> -20879 | C115: =B59-C59 -> -13056.198 | D115: =C59-D59 -> -13491.672 | E115: =D59-E59 -> -13789.122 | F115: =E59-F59 -> -13881.297 | G115: =F59-G59 -> -13747.3
A116: (-/+) Increase / Decrease in Trade Receivables | B116: ='03_Consolidated_Balance_Sheet_'!E21-'03_Consolidated_Balance_Sheet_'!F21 -> -16370 | C116: =B61-C61 -> -4888.295 | D116: =C61-D61 -> -4750.5886 | E116: =D61-E61 -> -4855.3246 | F116: =E61-F61 -> -4887.7808 | G116: =F61-G61 -> -4840.5984
A117: (+/-) Increase / Decrease in Trade Payables | B117: =-('03_Consolidated_Balance_Sheet_'!N24-'03_Consolidated_Balance_Sheet_'!M24) -> 27947 | C117: =C90-B90 -> 12282.096 | D117: =D90-C90 -> 12826.589 | E117: =E90-D90 -> 13109.376 | F117: =F90-E90 -> 13197.008 | G117: =G90-F90 -> 13069.616
A119: Net Cash Flow from Operating Activities (A) | B119: =SUM(B114:B117) -> 190309 | C119: =SUM(C114:C117) -> 204669.86 | D119: =SUM(D114:D117) -> 226156.3 | E119: =SUM(E114:E117) -> 248326.22 | F119: =SUM(F114:F117) -> 271371.69 | G119: =SUM(G114:G117) -> 295010.42
A121: CASH FLOW FROM OPERATING ACTIVITIES
A122: (-) Outflow for Fixed Assets (CAPEX / PPE Additions) | B122: ='04_Consolidated_Cash_Flow'!F8 -> -122916 | C122: =B122*(1+'07_Forecast_assumptions'!C106) -> -131813.12 | D122: =C122*(1+'07_Forecast_assumptions'!D106) -> -139446.03 | E122: =D122*(1+'07_Forecast_assumptions'!E106) -> -145905.95 | F122: =E122*(1+'07_Forecast_assumptions'!F106) -> -151313.29 | G122: =F122*(1+'07_Forecast_assumptions'!G106) -> -103523.23
A123: (-/+) Net Additions to Capital Work-in-Progress (CWIP) | B123: 0 | C123: 0 | D123: 0 | E123: 0 | F123: 0 | G123: 0
A125: Net Cash Flow from Investing Activities (B) | B125: =SUM(B122:B123) -> -122916 | C125: =SUM(C122:C123) -> -131813.12 | D125: =SUM(D122:D123) -> -139446.03 | E125: =SUM(E122:E123) -> -145905.95 | F125: =SUM(F122:F123) -> -151313.29 | G125: =SUM(G122:G123) -> -103523.23
A127: CASH FLOW FROM FINANCING ACTIVITIES
A128: (-/+) Net Repayment of Long-Term Borrowings | B128: =B79-'03_Consolidated_Balance_Sheet_'!M14 -> 33852 | C128: =C79-B79 -> -26346.307 | D128: =D79-C79 -> -23782.594 | E128: =E79-D79 -> -21468.351 | F128: =F79-E79 -> -19379.303 | G128: =G79-F79 -> -17493.537
A129: (-) Repayment of Deferred Payment (Spectrum) Liab. | B129: =B49-B49 -> 0 | C129: =C49-B49 -> 0 | D129: =D49-C49 -> 0 | E129: =E49-D49 -> 0 | F129: =F49-E49 -> 0 | G129: =G49-F49 -> 0
A130: -) Finance Costs (Interest Paid Out) | B130: =B29 -> -27061 | C130: =C29 -> -29694.259 | D130: =D29 -> -32583.755 | E130: =E29 -> -35754.423 | F130: =F29 -> -39233.624 | G130: =G29 -> -43051.379
A131: (-) Dividends Paid (Equity Shareholders) | B131: ='04_Consolidated_Cash_Flow'!F13 -> -7443 | C131: =B131 -> -7443 | D131: =C131 -> -7443 | E131: =D131 -> -7443 | F131: =E131 -> -7443 | G131: =F131 -> -7443
A133: Net Cash Flow from Financing Activities (C) | B133: =SUM(B128:B131) -> -652 | C133: =SUM(C128:C131) -> -63483.566 | D133: =SUM(D128:D131) -> -63809.349 | E133: =SUM(E128:E131) -> -64665.775 | F133: =SUM(F128:F131) -> -66055.927 | G133: =SUM(G128:G131) -> -67987.917
...

Sheet 08A_Balance_Sheet_Support_Sched
B3: Projected Line Item | C3: FY 2025-26 (Act) | D3: FY 2026-27 (Proj) | E3: FY 2027-28 (Proj) | F3: FY 2028-29 (Proj) | G3: FY 2029-30 (Proj) | H3: FY 2030-31 (Proj)
B4: PROPERTY, PLANT & EQUIPMENT SCHEDULE (₹ Crore)
B5: Opening PP&E | C5: - | D5: 751087 | E5: 820886 | F5: 894585 | G5: 971340 | H5: 1050124
B6: (+) Capitalisation from CWIP | C6: =C24 -> 0 | D6: =-'08_Three_Statement_Projections'!C122 -> 131813.12 | E6: =-'08_Three_Statement_Projections'!D122 -> 139446.03 | F6: =-'08_Three_Statement_Projections'!E122 -> 145905.95 | G6: =-'08_Three_Statement_Projections'!F122 -> 151313.29 | H6: =-'08_Three_Statement_Projections'!G122 -> 103523.23
B7: Depreciation | C7: =-'08_Three_Statement_Projections'!B27 -> -57688 | D7: =-'08_Three_Statement_Projections'!C27 -> -62014.6 | E7: =-'08_Three_Statement_Projections'!D27 -> -66665.695 | F7: =-'08_Three_Statement_Projections'!E27 -> -71665.622 | G7: =-'08_Three_Statement_Projections'!F27 -> -77040.544 | H7: =-'08_Three_Statement_Projections'!G27 -> -82818.585
B8: Closing PP&E | C8: =D5 -> 751087 | D8: =D5+D6+D7 -> 820885.52 | E8: =E5+E6+E7 -> 893666.33 | F8: =F5+F6+F7 -> 968825.33 | G8: =G5+G6+G7 -> 1045612.7 | H8: =H5+H6+H7 -> 1070828.6
B10: WORKING CAPITAL SCHEDULE
B11: Inventories | C11: ='03_Consolidated_Balance_Sheet_'!F19 -> 166941 | D11: ='08_Three_Statement_Projections'!C14*14.2% -> 179997.2 | E11: ='08_Three_Statement_Projections'!D14*14.2% -> 193488.87 | F11: ='08_Three_Statement_Projections'!E14*14.2% -> 207277.99 | G11: ='08_Three_Statement_Projections'!F14*14.2% -> 221159.29 | H11: ='08_Three_Statement_Projections'!G14*14.2% -> 234906.59
B12: Trade Receivables | C12: ='03_Consolidated_Balance_Sheet_'!F21 -> 58491 | D12: ='08_Three_Statement_Projections'!C14*5% -> 63379.295 | E12: ='08_Three_Statement_Projections'!D14*5% -> 68129.884 | F12: ='08_Three_Statement_Projections'!E14*5% -> 72985.208 | G12: ='08_Three_Statement_Projections'!F14*5% -> 77872.989 | H12: ='08_Three_Statement_Projections'!G14*5% -> 82713.587
B13: Trade Payable | C13: ='03_Consolidated_Balance_Sheet_'!N24 -> 158842 | D13: ='08_Three_Statement_Projections'!C14*13.5% -> 171124.1 | E13: ='08_Three_Statement_Projections'!D14*13.5% -> 183950.69 | F13: ='08_Three_Statement_Projections'!E14*13.5% -> 197060.06 | G13: ='08_Three_Statement_Projections'!F14*13.5% -> 210257.07 | H13: ='08_Three_Statement_Projections'!G14*13.5% -> 223326.69
B16: NCI SCHEDULE
B17: Opening NCI | C17: ='08_Three_Statement_Projections'!B74 -> 181836 | D17: =C19 -> 181836 | E17: =D19 -> 202088 | F17: =E19 -> 224697 | G17: =F19 -> 249725 | H17: =G19 -> 277182
B18: + Share of PAT to NCI | C18: - | D18: 20252 | E18: 22609 | F18: 25028 | G18: 27457 | H18: 29828
B19: Closing NCI | C19: =SUM(C17:C18) -> 181836 | D19: =SUM(D17:D18) -> 202088 | E19: =SUM(E17:E18) -> 224697 | F19: =SUM(F17:F18) -> 249725 | G19: =SUM(G17:G18) -> 277182 | H19: =SUM(H17:H18) -> 307010

Sheet 09_Free_Cash_Flow_Schedule FCFF
A1: RELIANCE INDUSTRIES LIMITED
A2: FREE CASH FLOW SCHEDULE
A3: (₹ in Crore)
A5: Projected Line Item | B5: FY 2026-27 (Proj) | C5: FY 2027-28 (Proj) | D5: FY 2028-29 (Proj) | E5: FY 2029-30 (Proj) | F5: FY 2030-31 (Proj)
A6: EBIT (Operating Profit) | B6: ='08_Three_Statement_Projections'!C28 -> 168003.51 | C6: ='08_Three_Statement_Projections'!D28 -> 188189.27 | D6: ='08_Three_Statement_Projections'!E28 -> 209166.4 | E6: ='08_Three_Statement_Projections'!F28 -> 230545.5 | F6: ='08_Three_Statement_Projections'!G28 -> 251887.78
A7: Tax Rate % | B7: ='07_Forecast_assumptions'!C6 -> 25.17 | C7: ='07_Forecast_assumptions'!D6 -> 25.17 | D7: ='07_Forecast_assumptions'!E6 -> 25.17 | E7: ='07_Forecast_assumptions'!F6 -> 25.17 | F7: ='07_Forecast_assumptions'!G6 -> 25.17
A8: Tax on EBIT | B8: =B6*B7% -> 42286.483 | C8: =C6*C7% -> 47367.24 | D8: =D6*D7% -> 52647.183 | E8: =E6*E7% -> 58028.302 | F8: =F6*F7% -> 63400.155
A9: NOPAT | B9: =B6-B8 -> 125717.02 | C9: =C6-C8 -> 140822.03 | D9: =D6-D8 -> 156519.22 | E9: =E6-E8 -> 172517.2 | F9: =F6-F8 -> 188487.63
A11: (+) Depreciation & Amortisation | B11: ='08_Three_Statement_Projections'!C27 -> 62014.6 | C11: ='08_Three_Statement_Projections'!D27 -> 66665.695 | D11: ='08_Three_Statement_Projections'!E27 -> 71665.622 | E11: ='08_Three_Statement_Projections'!F27 -> 77040.544 | F11: ='08_Three_Statement_Projections'!G27 -> 82818.585
A12: (-) Capital Expenditure (CAPEX) | B12: ='08_Three_Statement_Projections'!C122 -> -131813.12 | C12: ='08_Three_Statement_Projections'!D122 -> -139446.03 | D12: ='08_Three_Statement_Projections'!E122 -> -145905.95 | E12: ='08_Three_Statement_Projections'!F122 -> -151313.29 | F12: ='08_Three_Statement_Projections'!G122 -> -103523.23
A13: (-) Increase in Net Working Capital | B13: =-'08_Three_Statement_Projections'!C115-'08_Three_Statement_Projections'!C116-'08_Three_Statement_Projections'!C117 -> 5662.3963 | C13: =-'08_Three_Statement_Projections'!D115-'08_Three_Statement_Projections'!D116-'08_Three_Statement_Projections'!D117 -> 5415.671 | D13: =-'08_Three_Statement_Projections'!E115-'08_Three_Statement_Projections'!E116-'08_Three_Statement_Projections'!E117 -> 5535.0701 | E13: =-'08_Three_Statement_Projections'!F115-'08_Three_Statement_Projections'!F116-'08_Three_Statement_Projections'!F117 -> 5572.0701 | F13: =-'08_Three_Statement_Projections'!G115-'08_Three_Statement_Projections'!G116-'08_Three_Statement_Projections'!G117 -> 5518.2822
A15: Free Cash Flow to Firm (FCFF) | B15: =B9+B11+B12-B13 -> 50256.106 | C15: =C9+C11+C12-C13 -> 62626.031 | D15: =D9+D11+D12-D13 -> 76743.823 | E15: =E9+E11+E12-E13 -> 92672.376 | F15: =F9+F11+F12-F13 -> 162264.7

Sheet 10_DCF_Valuation
B1: RELIANCE INDUSTRIES LIMITED
B2: DCF VALUATION
B3: (₹ in Crore)
C5: Terminal Growth Rate | D5: ='07_Forecast_assumptions'!C11 -> 5
C6: WACC % | D6: ='07_Forecast_assumptions'!C7 -> 10.5
B8: Projected Line Item | C8: FY 2026-27 (Proj) | D8: FY 2027-28 (Proj) | E8: FY 2028-29 (Proj) | F8: FY 2029-30 (Proj) | G8: FY 2030-31 (Proj)
B9: Projection Year (t) | C9: 1 | D9: 2 | E9: 3 | F9: 4 | G9: 5
B10: Free Cash Flow (FCFF) | C10: ='09_Free_Cash_Flow_Schedule FCFF'!B15 -> 50256.106 | D10: ='09_Free_Cash_Flow_Schedule FCFF'!C15 -> 62626.031 | E10: ='09_Free_Cash_Flow_Schedule FCFF'!D15 -> 76743.823 | F10: ='09_Free_Cash_Flow_Schedule FCFF'!E15 -> 92672.376 | G10: ='09_Free_Cash_Flow_Schedule FCFF'!F15 -> 162264.7
B11: Discount Factor (@10.50%) | C11: =1/(1+$D$6/100)^C9 -> 0.90497738 | D11: =1/(1+$D$6/100)^D9 -> 0.81898405 | E11: =1/(1+$D$6/100)^E9 -> 0.74116204 | F11: =1/(1+$D$6/100)^F9 -> 0.67073487 | G11: =1/(1+$D$6/100)^G9 -> 0.60699989
B13: Present Value (PV) of FCF | C13: =C10*C11 -> 45480.639 | D13: =D10*D11 -> 51289.72 | E13: =E10*E11 -> 56879.608 | F13: =F10*F11 -> 62158.595 | G13: =G10*G11 -> 98494.654
B16: Particular | C16: Amount
B17: FY2030-31 FCFF | C17: =G10 -> 162264.7
B18: Terminal Growth Rate | C18: =D5/100 -> 0.05
B19: WACC | C19: =D6/100 -> 0.105
B20: Terminal Value | C20: =C17*(1+C18)/(C19 -C18) -> 3097780.6
B21: Discount Factor (FY2030-31) | C21: =G11 -> 0.60699989
B22: Present Value of Terminal Value | C22: =C20*C21 -> 1880352.5
B25: Particular | C25: Amount
B26: PV of Explicit FCFF | C26: =SUM(C13:G13) -> 314303.21
B27: Present Value of Terminal Value | C27: =C22 -> 1880352.5
B28: Enterprise Value | C28: =C27+C26 -> 2194655.7
B31: Particular | C31: Amount
B32: Enterprise Value | C32: =C28 -> 2194655.7
B33: (+) Cash & Cash Equivalents | C33: ='08_Three_Statement_Projections'!C62 -> 155350.17
B34: (-) Total Debt | C34: ='08_Three_Statement_Projections'!C79+'08_Three_Statement_Projections'!C88 -> 348074.69
B35: (-) Non-Controlling Interest (NCI) | C35: =-'15_DCF_Sensitivity_Analysis'!C23 -> -181836
B36: Equity Value | C36: =C32+C33-C34+C35 -> 1820095.2
B37: Shares Outstanding (Crore) | C37: =1353.25 -> 1353.25
B39: Implied Share Price | C39: =C36/C37 -> 1344.9807

Sheet 11_SOTP_valuation
A1: RELIANCE INDUSTRIES LIMITED
A2: SOTP VALUATION
A3: (₹ in Crore)
A5: Segment | B5: FY2026-27 EBITDA (₹ Cr) | C5: EV/EBITDA Multiple | D5: Enterprise Value (₹ Cr)
A6: Oil-to-Chemicals (O2C) | B6: ='08_Three_Statement_Projections'!C17 -> 66526.374 | C6: ='07_Forecast_assumptions'!C29 -> 6.5 | D6: =B6*C6 -> 432421.43
A7: Digital Services (Jio) | B7: ='08_Three_Statement_Projections'!C18 -> 85028.312 | C7: ='07_Forecast_assumptions'!C49 -> 15 | D7: =B7*C7 -> 1275424.7
A8: Reliance Retail | B8: ='08_Three_Statement_Projections'!C19 -> 29876.355 | C8: ='07_Forecast_assumptions'!C75 -> 22 | D8: =B8*C8 -> 657279.81
A9: Oil & Gas (E&P) | B9: ='08_Three_Statement_Projections'!C20 -> 20565.521 | C9: ='07_Forecast_assumptions'!C94 -> 5.5 | D9: =B9*C9 -> 113110.37
A10: Other Businesses & Corporate | B10: ='08_Three_Statement_Projections'!C21 -> 28021.545 | C10: 8 | D10: =B10*C10 -> 224172.36
A12: Total Enterprise Value | D12: =SUM(D6:D10) -> 2702408.6
A15: Particular | B15: Amount
A16: Total Enterprise Value | B16: =D12 -> 2702408.6
A17: (+) Cash & Cash Equivalents | B17: ='08_Three_Statement_Projections'!C62 -> 155350.17
A18: (-) Total Debt | B18: =-('08_Three_Statement_Projections'!C79+'08_Three_Statement_Projections'!C88) -> -348074.69
A19: (-) Non-Controlling Interest | B19: =-(D7*0.33+D8*0.15) -> -519482.12
A20: Equity Value | B20: =B16+B17+B18+B19 -> 1990202
A21: Shares Outstanding (Cr) | B21: 1353.25
A23: Implied Share Price | B23: =B20*(1+'07_Forecast_assumptions'!C15/100)/B21 -> 1397.149
A26: SOTP SENSITIVITY ANALYSIS
A27: Jio EV/EBITDA vs Retail EV/EBITDA
B30: =B23 -> 1397.149 | C30: 18 | D30: 20 | E30: 22 | F30: 24 | G30: 26
B31: 13 | C31: 1245.8528 | D31: 1281.5079 | E31: 1317.163 | F31: 1352.8182 | G31: 1388.4733
B32: 14 | C32: 1285.8457 | D32: 1321.5009 | E32: 1357.156 | F32: 1392.8112 | G32: 1428.4663
B33: 15 | C33: 1325.8387 | D33: 1361.4939 | E33: 1397.149 | F33: 1432.8042 | G33: 1468.4593
B34: 16 | C34: 1365.8317 | D34: 1401.4869 | E34: 1437.142 | F34: 1472.7971 | G34: 1508.4523
B35: 17 | C35: 1405.8247 | D35: 1441.4799 | E35: 1477.135 | F35: 1512.7901 | G35: 1548.4453

Sheet 12_Scenario_Analysis_Dashboard
A1: SCENARIO ANALYSIS DASHBOARD
A5: Scenario-Based Valuation Dashboard | B5: Bull Case (Switch = 1) | C5: Base Case (Switch = 2) | D5: Bear Case (Switch = 3)
A6: Jio Subscriber Growth FY27 | B6: ='07_Forecast_assumptions'!C58 -> 0.094149939 | C6: ='07_Forecast_assumptions'!C59 -> 0.074149939 | D6: ='07_Forecast_assumptions'!C60 -> 0.054149939
A7: Retail EBITDA Margin FY27 | B7: ='07_Forecast_assumptions'!C72 -> 0.095270473 | C7: ='07_Forecast_assumptions'!C73 -> 0.080270473 | D7: ='07_Forecast_assumptions'!C74 -> 0.065270473
A8: O2C GRM Assumption ($/bbl) FY27 | B8: ='07_Forecast_assumptions'!C35 -> 13.03 | C8: ='07_Forecast_assumptions'!C36 -> 10.78 | D8: ='07_Forecast_assumptions'!C37 -> 8.53
A9: Consolidated EBITDA FY27 | B9: 240759 | C9: 230018 | D9: 219544
A10: DCF Target Price | B10: 1934.85 | C10: 1344.98 | D10: 624.36
A11: SOTP Target Price | B11: 1834.64 | C11: 1397.15 | D11: 1034.12
A12: Weighted Target Price (DCF:0.2, SOTP:0.8) | B12: =B10*0.2 +B11*0.8 -> 1854.682 | C12: =C10*0.2 +C11*0.8 -> 1386.716 | D12: =D10*0.2 +D11*0.8 -> 952.168
A13: Current NSE Price (₹) | B13: ='13_Executive_Summary'!B9 -> 1310 | C13: =B13 -> 1310 | D13: =C13 -> 1310
A14: Implied Upside / (Downside) | B14: =B12/B13-1 -> 0.41578779 | C14: =C12/C13-1 -> 0.058561832 | D14: =D12/D13-1 -> -0.2731542
A15: Recommendation | B15: =IF(B14>25%,"STRONG BUY",IF(B14>20%,"BUY",IF(B14>0%,"HOLD","SELL"))) -> STRONG BUY | C15: =IF(C14>25%,"STRONG BUY",IF(C14>20%,"BUY",IF(C14>0%,"HOLD","SELL"))) -> HOLD | D15: =IF(D14>25%,"STRONG BUY",IF(D14>20%,"BUY",IF(D14>0%,"HOLD","SELL"))) -> SELL

Sheet 13_Executive_Summary
A1: RELIANCE INDUSTRIES LIMITED
A2: Valuation Summary & Investment Thesis
A4: MASTER INVESTOR BRIEFCASE
A6: Valuation Metric | B6: Output Cell
A7: SOTP Intrinsic Target Price | B7: ='11_SOTP_valuation'!B23 -> 1397.149
A8: DCF Intrinsic Target Price | B8: ='10_DCF_Valuation'!C39 -> 1344.9807
A9: Current NSE Market Price (As of Aug 12, 2026) | B9: 1310
A10: Weighted Target Price (DCF:0.2, SOTP:0.8) | B10: =B8*0.2 +B7*0.8 -> 1386.7154
A11: Implied SOTP Upside/ (Downside) (%) | B11: =B7/B9-1 -> 0.066525967
A12: Weighted Target Upside/ Downside (%) | B12: =B10/B9-1 -> 0.058561343
A13: RECOMMENDATION | B13: =IF(B12>25%,"STRONG BUY", IF(B12>15%,"BUY", IF(B12>0%,"HOLD","SELL"))) -> HOLD
A16: CONSOLIDATED OPERATION & METRIC FORWARD TRACK
A18: Key Group Health Performance Metric | B18: FY 2025-26 (Act) | C18: FY 2026-27 (Proj) | D18: FY 2027-28 (Proj) | E18: FY 2028-29 (Proj) | F18: FY 2029-30 (Proj) | G18: FY 2030-31 (Proj)
A19: Revenue from Operations (₹ Cr) | B19: ='08_Three_Statement_Projections'!B14 -> 1175919 | C19: ='08_Three_Statement_Projections'!C14 -> 1267585.9 | D19: ='08_Three_Statement_Projections'!D14 -> 1362597.7 | E19: ='08_Three_Statement_Projections'!E14 -> 1459704.2 | F19: ='08_Three_Statement_Projections'!F14 -> 1557459.8 | G19: ='08_Three_Statement_Projections'!G14 -> 1654271.7
A20: EBITDA (₹ Cr) | B20: ='08_Three_Statement_Projections'!B23 -> 207911 | C20: ='08_Three_Statement_Projections'!C23 -> 230018.11 | D20: ='08_Three_Statement_Projections'!D23 -> 254854.97 | E20: ='08_Three_Statement_Projections'!E23 -> 280832.02 | F20: ='08_Three_Statement_Projections'!F23 -> 307586.04 | G20: ='08_Three_Statement_Projections'!G23 -> 334706.37
A21: EBITDA Margin (%) | B21: =B20/B19 -> 0.17680725 | C21: =C20/C19 -> 0.18146155 | D21: =D20/D19 -> 0.18703611 | E21: =E20/E19 -> 0.19238968 | F21: =F20/F19 -> 0.19749213 | G21: =G20/G19 -> 0.20232853
A22: PAT (Attributable to Owners) (₹ Cr) | B22: ='08_Three_Statement_Projections'!B41 -> 95754 | C22: ='08_Three_Statement_Projections'!C41 -> 98371.185 | D22: ='08_Three_Statement_Projections'!D41 -> 109714.47 | E22: ='08_Three_Statement_Projections'!E41 -> 121412.82 | F22: ='08_Three_Statement_Projections'!F41 -> 133213.16 | G22: ='08_Three_Statement_Projections'!G41 -> 144830.68
A25: STRATEGIC COMPONENT BREAKDOWN (SOTP CONTRIBUTION)
A27: Business Vertical | B27: Enterprise Value Contribution | C27: % of Corporate Value
A28: Digital Services (Jio) | B28: ='11_SOTP_valuation'!D7 -> 1275424.7 | C28: =B28/'11_SOTP_valuation'!$D$12 -> 0.47195848
A29: Reliance Retail | B29: ='11_SOTP_valuation'!D8 -> 657279.81 | C29: =B29/'11_SOTP_valuation'!$D$12 -> 0.24321999
A30: O2C | B30: ='11_SOTP_valuation'!D6 -> 432421.43 | C30: =B30/'11_SOTP_valuation'!$D$12 -> 0.16001334
A31: Other Businesses & Corporate | B31: ='11_SOTP_valuation'!D10 -> 224172.36 | C31: =B31/'11_SOTP_valuation'!$D$12 -> 0.082952799
A32: Oil & Gas (E&P) | B32: ='11_SOTP_valuation'!D9 -> 113110.37 | C32: =B32/'11_SOTP_valuation'!$D$12 -> 0.04185539

Sheet 14_Key_Metrics_Dashboard
A1: RELIANCE INDUSTRIES LIMITED
A3: FINANCIAL PERFORMANCE
A5: Metric | B5: FY 2025-26 (Act) | C5: FY 2026-27 (Proj) | D5: FY 2027-28 (Proj) | E5: FY 2028-29 (Proj) | F5: FY 2029-30 (Proj) | G5: FY 2030-31 (Proj)
A6: Revenue from Operations | B6: ='08_Three_Statement_Projections'!B14 -> 1175919 | C6: ='08_Three_Statement_Projections'!C14 -> 1267585.9 | D6: ='08_Three_Statement_Projections'!D14 -> 1362597.7 | E6: ='08_Three_Statement_Projections'!E14 -> 1459704.2 | F6: ='08_Three_Statement_Projections'!F14 -> 1557459.8 | G6: ='08_Three_Statement_Projections'!G14 -> 1654271.7
A7: EBITDA | B7: ='08_Three_Statement_Projections'!B23 -> 207911 | C7: ='08_Three_Statement_Projections'!C23 -> 230018.11 | D7: ='08_Three_Statement_Projections'!D23 -> 254854.97 | E7: ='08_Three_Statement_Projections'!E23 -> 280832.02 | F7: ='08_Three_Statement_Projections'!F23 -> 307586.04 | G7: ='08_Three_Statement_Projections'!G23 -> 334706.37
A8: EBITDA Margin | B8: =B7/B6 -> 0.17680725 | C8: =C7/C6 -> 0.18146155 | D8: =D7/D6 -> 0.18703611 | E8: =E7/E6 -> 0.19238968 | F8: =F7/F6 -> 0.19749213 | G8: =G7/G6 -> 0.20232853
A9: PAT (Attributable) | B9: ='08_Three_Statement_Projections'!B41 -> 95754 | C9: ='08_Three_Statement_Projections'!C41 -> 98371.185 | D9: ='08_Three_Statement_Projections'!D41 -> 109714.47 | E9: ='08_Three_Statement_Projections'!E41 -> 121412.82 | F9: ='08_Three_Statement_Projections'!F41 -> 133213.16 | G9: ='08_Three_Statement_Projections'!G41 -> 144830.68
A10: PAT Margin | B10: =B9/B6 -> 0.081429078 | C10: =C9/C6 -> 0.077605143 | D10: =D9/D6 -> 0.080518609 | E10: =E9/E6 -> 0.08317632 | F10: =F9/F6 -> 0.085532329 | G10: =G9/G6 -> 0.087549507
A11: FCFF | B11: - | C11: ='09_Free_Cash_Flow_Schedule FCFF'!B15 -> 50256.106 | D11: ='09_Free_Cash_Flow_Schedule FCFF'!C15 -> 62626.031 | E11: ='09_Free_Cash_Flow_Schedule FCFF'!D15 -> 76743.823 | F11: ='09_Free_Cash_Flow_Schedule FCFF'!E15 -> 92672.376 | G11: ='09_Free_Cash_Flow_Schedule FCFF'!F15 -> 162264.7
A14: BALANCE SHEET STRENGTH
A16: Metric | B16: FY 2025-26 (Act) | C16: FY 2026-27 (Proj) | D16: FY 2027-28 (Proj) | E16: FY 2028-29 (Proj) | F16: FY 2029-30 (Proj) | G16: FY 2030-31 (Proj)
A17: Total Debt | B17: ='08_Three_Statement_Projections'!B79+'08_Three_Statement_Projections'!B88 -> 374421 | C17: ='08_Three_Statement_Projections'!C79+'08_Three_Statement_Projections'!C88 -> 348074.69 | D17: ='08_Three_Statement_Projections'!D79+'08_Three_Statement_Projections'!D88 -> 324292.1 | E17: ='08_Three_Statement_Projections'!E79+'08_Three_Statement_Projections'!E88 -> 302823.75 | F17: ='08_Three_Statement_Projections'!F79+'08_Three_Statement_Projections'!F88 -> 283444.44 | G17: ='08_Three_Statement_Projections'!G79+'08_Three_Statement_Projections'!G88 -> 265950.91
A18: Cash & Equivalents | B18: ='08_Three_Statement_Projections'!B62 -> 145977 | C18: ='08_Three_Statement_Projections'!C139 -> 155350.17 | D18: ='08_Three_Statement_Projections'!D139 -> 178251.1 | E18: ='08_Three_Statement_Projections'!E139 -> 216005.59 | F18: ='08_Three_Statement_Projections'!F139 -> 270008.06 | G18: ='08_Three_Statement_Projections'!G139 -> 393507.33
A19: Net Debt | B19: =B17-B18 -> 228444 | C19: =C17-C18 -> 192724.52 | D19: =D17-D18 -> 146041 | E19: =E17-E18 -> 86818.154 | F19: =F17-F18 -> 13436.385 | G19: =G17-G18 -> -127556.42
A20: Net Debt / EBITDA | B20: =B19/B7 -> 1.0987586 | C20: =C19/C7 -> 0.83786675 | D20: =D19/D7 -> 0.57303573 | E20: =E19/E7 -> 0.3091462 | F20: =F19/F7 -> 0.043683339 | G20: =G19/G7 -> -0.38109949
A21: Total Equity | B21: ='08_Three_Statement_Projections'!B76 -> 1085866 | C21: ='08_Three_Statement_Projections'!C76 -> 1176794.2 | D21: ='08_Three_Statement_Projections'!D76 -> 1279065.7 | E21: ='08_Three_Statement_Projections'!E76 -> 1393035.5 | F21: ='08_Three_Statement_Projections'!F76 -> 1518805.6 | G21: ='08_Three_Statement_Projections'!G76 -> 1656193.3
A24: GROWTH SUMMARY
A26: Metric | B26: CAGR FY26-31
A27: Revenue CAGR | B27: =(G6/C6)^(1/5)-1 -> 0.05469258
A28: EBITDA CAGR | B28: =(G7/C7)^(1/5)-1 -> 0.077904759
A29: PAT CAGR | B29: =(G9/C9)^(1/5)-1 -> 0.080434718
A30: FCFF CAGR | B30: =(G11/C11)^(1/5)-1 -> 0.26417455
A33: RETURN METRICS
A35: Metric | B35: FY 2026-27 (Proj) | C35: FY 2027-28 (Proj) | D35: FY 2028-29 (Proj) | E35: FY 2029-30 (Proj) | F35: FY 2030-31 (Proj)
A36: ROE (PAT / Average Equity) | B36: =C9/((C21+B21)/2) -> 0.086951797 | C36: =D9/((D21+C21)/2) -> 0.089349129 | D36: =E9/((E21+D21)/2) -> 0.09087442 | E36: =F9/((F21+E21)/2) -> 0.091497549 | F36: =G9/((G21+F21)/2) -> 0.091231952
A37: ROCE (EBIT / Average Capital Employed) | B37: ='08_Three_Statement_Projections'!C28/('14_Key_Metrics_Dashboard'!C21+'14_Key_Metrics_Dashboard'!C19) -> 0.12267339 | C37: ='08_Three_Statement_Projections'!D28/('14_Key_Metrics_Dashboard'!D21+'14_Key_Metrics_Dashboard'!D19) -> 0.13205276 | D37: ='08_Three_Statement_Projections'!E28/('14_Key_Metrics_Dashboard'!E21+'14_Key_Metrics_Dashboard'!E19) -> 0.14134263 | E37: ='08_Three_Statement_Projections'!F28/('14_Key_Metrics_Dashboard'!F21+'14_Key_Metrics_Dashboard'!F19) -> 0.15046285 | F37: ='08_Three_Statement_Projections'!G28/('14_Key_Metrics_Dashboard'!G21+'14_Key_Metrics_Dashboard'!G19) -> 0.16477934
A38: DuPont Drivers (ROE Decomposition):
A39: ├── Net Profit Margin (%) | B39: =C9/('08_Three_Statement_Projections'!C30+'14_Key_Metrics_Dashboard'!C6) -> 0.076386975 | C39: =D9/('08_Three_Statement_Projections'!D30+'14_Key_Metrics_Dashboard'!D6) -> 0.0792836 | D39: =E9/('08_Three_Statement_Projections'!E30+'14_Key_Metrics_Dashboard'!E6) -> 0.081925491 | E39: =F9/('08_Three_Statement_Projections'!F30+'14_Key_Metrics_Dashboard'!F6) -> 0.084266224 | F39: =G9/('08_Three_Statement_Projections'!G30+'14_Key_Metrics_Dashboard'!G6) -> 0.086268162
A40: ├── Asset Turnover (x) | B40: =('08_Three_Statement_Projections'!C30 + '08_Three_Statement_Projections'!C14) / ('08_Three_Statement_Projections'!C69+'08_Three_Statement_Projections'!C67) -> 0.57028894 | C40: =('08_Three_Statement_Projections'!D30 + '08_Three_Statement_Projections'!D14) / ('08_Three_Statement_Projections'!D69+'08_Three_Statement_Projections'!D67) -> 0.58799587 | D40: =('08_Three_Statement_Projections'!E30 + '08_Three_Statement_Projections'!E14) / ('08_Three_Statement_Projections'!E69+'08_Three_Statement_Projections'!E67) -> 0.60147076 | E40: =('08_Three_Statement_Projections'!F30 + '08_Three_Statement_Projections'!F14) / ('08_Three_Statement_Projections'!F69+'08_Three_Statement_Projections'!F67) -> 0.6105227 | F40: =('08_Three_Statement_Projections'!G30 + '08_Three_Statement_Projections'!G14) / ('08_Three_Statement_Projections'!G69+'08_Three_Statement_Projections'!G67) -> 0.61515223
A41: └── Equity Multiplier (x) | B41: =('08_Three_Statement_Projections'!C69+'08_Three_Statement_Projections'!C67)/AVERAGE(C21,B21) -> 1.9960173 | C41: =('08_Three_Statement_Projections'!D69+'08_Three_Statement_Projections'!D67)/AVERAGE(D21,C21) -> 1.9166053 | D41: =('08_Three_Statement_Projections'!E69+'08_Three_Statement_Projections'!E67)/AVERAGE(E21,D21) -> 1.8442003 | E41: =('08_Three_Statement_Projections'!F69+'08_Three_Statement_Projections'!F67)/AVERAGE(F21,E21) -> 1.778501 | F41: =('08_Three_Statement_Projections'!G69+'08_Three_Statement_Projections'!G67)/AVERAGE(G21,F21) -> 1.7191502
A43: SEGMENT EBITDA CONTRIBUTION
A45: Segment | B45: FY2026-27 EBITDA | C45: % Contribution
A46: Digital Services (Jio) | B46: ='08_Three_Statement_Projections'!C18 -> 85028.312 | C46: =B46/$C$7 -> 0.36965921
A47: O2C | B47: ='08_Three_Statement_Projections'!C17 -> 66526.374 | C47: =B47/$C$7 -> 0.28922233
A48: Reliance Retail | B48: ='08_Three_Statement_Projections'!C19 -> 29876.355 | C48: =B48/$C$7 -> 0.12988697
A49: Other Businesses & Corporate | B49: ='08_Three_Statement_Projections'!C21 -> 28021.545 | C49: =B49/$C$7 -> 0.12182321
A50: Oil & Gas (E&P) | B50: ='08_Three_Statement_Projections'!C20 -> 20565.521 | C50: =B50/$C$7 -> 0.089408271

Sheet 15_DCF_Sensitivity_Analysis
B1: RELIANCE INDUSTRIES LIMITED
B2: DCF SENSITIVITY ANALYSIS
B3: WACC vs Terminal Growth Rate Sensitivity
C4: =C26 -> 1344.9807 | D4: 0.04 | E4: =D4+0.5% -> 0.045 | F4: =E4+0.5% -> 0.05 | G4: =F4+0.5% -> 0.055 | H4: =G4+0.5% -> 0.06
C5: 0.095 | D5: 1395.7493 | E5: 1547.3938 | F5: 1732.7372 | G5: 1964.4164 | H5: 2262.2896
C6: =C5+0.5% -> 0.1 | D6: 1245.992 | E6: 1370.0804 | F6: 1518.9865 | G6: 1700.9829 | H6: 1928.4784
C7: =C6+0.5% -> 0.105 | D7: 1120.0127 | E7: 1223.123 | F7: 1344.9807 | G7: 1491.21 | H7: 1669.9346
C8: =C7+0.5% -> 0.11 | D8: 1012.6947 | E8: 1099.4933 | F8: 1200.7583 | G8: 1320.4352 | H8: 1464.0474
C9: =C8+0.5% -> 0.115 | D9: 920.28649 | E9: 994.17166 | F9: 1079.4238 | G9: 1178.8846 | H9: 1296.4291
B12: Item | C12: Values
B13: FY31 FCFF | C13: ='09_Free_Cash_Flow_Schedule FCFF'!F15 -> 162264.7
B14: Terminal Growth | C14: ='07_Forecast_assumptions'!C11/100 -> 0.05
B15: WACC | C15: ='07_Forecast_assumptions'!C7/100 -> 0.105
B16: Terminal Value | C16: =C13*(1+C14)/(C15-C14) -> 3097780.6
B17: PV Terminal Value | C17: =C16/(1+C15)^5 -> 1880352.5
B18: PV Explicit FCFF | C18: ='10_DCF_Valuation'!C26 -> 314303.21
B19: Enterprise Value | C19: =C17+C18 -> 2194655.7
B21: Cash % Cash Equivalent | C21: ='08_Three_Statement_Projections'!C62 -> 155350.17
B22: Total Debt | C22: ='08_Three_Statement_Projections'!C79+'08_Three_Statement_Projections'!C88 -> 348074.69
B23: NCI | C23: ='08_Three_Statement_Projections'!C74 -> 181836
B24: Equity Value | C24: =C19+C21-C22-C23 -> 1820095.2
B25: Shares Outstanding (Cr) | C25: 1353.25
B26: Share Price | C26: =C24/C25 -> 1344.9807

Sheet 16_Relative_Valuation
A1: RELIANCE INDUSTRIES LIMITED
A3: VALUATION METHODLOGY
A5: Item | B5: Selection
A6: Valuation Date | B6: 12th August 2026
A7: Forecast Year | B7: FY2026-27E
A8: Primary Multiple | B8: EV/EBITDA
A9: Secondary Multiples | B9: P/E, EV/Sales, P/B
A10: Central Tendency | B10: Median
A11: Target Price Method | B11: Weighted Average
A12: Peer Selection | B12: Segment-relevent + diversified reference peers
A15: SEGMENT-RELEVANT COMPARABLE FRAMEWORK
A17: Reliance Segment | B17: Primary Comparable | C17: Rationale | D17: Relevence
A18: Digital Services (Jio) | B18: Bharti Airtel | C18: Direct listed telecom operator; closest operating and business-model comparable | D18: 5
A19: Reliance Retail | B19: Avenue Supermarts | C19: Indian organized retail exposure; store-led consumer model | D19: 5
A20: O2C | B20: Indian Oil | C20: Indian refining and petroleum marketing exposure | D20: 4
A21: Oil & Gas (E&P) | B21: ONGC | C21: Indian upstream oil & gas exposure | D21: 5
A22: Diversified / Corporate | B22: Adani Enterprises | C22: Diversified Indian business portfolio; useful conglomerate reference | D22: 3
A25: SEGMENT WEIGHTING FOR RELATIVE VALUATION
A27: Reliance Segment | B27: Valuation Basis | C27: Segment Value (₹ Cr) | D27: % of SOTP Value | E27: Comparable Weight
A28: Digital Services (Jio) | B28: SOTP EV | C28: ='11_SOTP_valuation'!D7 -> 1275424.7 | D28: =C28/$C$33 -> 0.47195848 | E28: 0.4654299
A29: Reliance Retail | B29: SOTP EV | C29: ='11_SOTP_valuation'!D8 -> 657279.81 | D29: =C29/$C$33 -> 0.24321999 | E29: 0.23362552
A30: O2C | B30: SOTP EV | C30: ='11_SOTP_valuation'!D6 -> 432421.43 | D30: =C30/$C$33 -> 0.16001334 | E30: 0.1690713
A31: Other Businesses & Corporate | B31: SOTP EV | C31: ='11_SOTP_valuation'!D10 -> 224172.36 | D31: =C31/$C$33 -> 0.082952799 | E31: 0.087648553
A32: Oil & Gas (E&P) | B32: SOTP EV | C32: ='11_SOTP_valuation'!D9 -> 113110.37 | D32: =C32/$C$33 -> 0.04185539 | E32: 0.044224721
A33: Total | C33: =SUM(C28:C32) -> 2702408.6 | D33: =C33/$C$33 -> 1
A36: PEER UNIVERSE
A38: Company | C38: Ticker | D38: Country | E38: Sector
A39: Reliance Industries | C39: RELIANCE | D39: India | E39: Conglomerate
A40: Bharti Airtel | C40: BHARTIARTL | D40: India | E40: Telecom
A41: Avenue Supermarts | C41: DMART | D41: India | E41: Retail
A42: Indian Oil | C42: IOC | D42: India | E42: Refining
A43: ONGC | C43: ONGC | D43: India | E43: Oil & Gas
A44: Adani Enterprises | C44: ADANIENT | D44: India | E44: Diversified
A47: SOTP SEGMENT VALUE WEIGHTS — DCF BASE CASE
A49: Reliance Segment | B49: Primary Peer | C49: Relevant Multiple | D49: Peer Multiple | E49: Reliance Metric | F49: Implied Segment EV
A50: Digital Services (Jio) | B50: Bharti Airtel | C50: EV/EBITDA | D50: =J97 -> 9.6365766 | E50: ='08_Three_Statement_Projections'!C18 -> 85028.312 | F50: =E50*D50 -> 819381.84
A51: Reliance Retail | B51: Avenue Supermarts | C51: EV/EBITDA | D51: =B69 -> 20.07 | E51: ='08_Three_Statement_Projections'!C19 -> 29876.355 | F51: =E51*D51 -> 599618.44
A52: O2C | B52: Indian Oil | C52: EV/EBITDA | D52: =J99 -> 3.6460721 | E52: ='08_Three_Statement_Projections'!C17 -> 66526.374 | F52: =E52*D52 -> 242559.95
A53: Oil & Gas (E&P) | B53: ONGC | C53: EV/EBITDA | D53: =J100 -> 2.1260064 | E53: ='08_Three_Statement_Projections'!C20 -> 20565.521 | F53: =E53*D53 -> 43722.431
A56: RETAIL COMPARABILITY ANALYSIS
A57: Metric | B57: Reliance Retail FY27E | C57: DMart FY27E | D57: Relative Assessment | F57: Notes
A58: Revenue Growth | B58: ='08_Three_Statement_Projections'!D10/'08_Three_Statement_Projections'!C10-1 -> 0.12404572 | C58: 0.2289 | D58: Dmart Higher
A59: EBITDA Margin | B59: ='08_Three_Statement_Projections'!C19/'08_Three_Statement_Projections'!C10 -> 0.080270473 | C59: =F98/E98 -> 0.07654921 | D59: Reliance Slightly high | F59: Selected below DMart's 39.9x observed multiple to reflect Reliance Retail's lower forecast growth,while maintaining a premium to the broader peer median due to its scale,
A60: EV/EBITDA | B60: 20.07 | C60: =J98 -> 41.36324 | D60: Reliance at ~50% discount | F60: margin profile and long-term organized-retail growth opportunity.
A63: RETAIL MULTIPLE NORMALIZATION
A65: Method | B65: EV/EBITDA Multiple | C65: Reliance Retail FY27E EBITDA | D65: Implied Retail EV | F65: Notes
A66: Raw DMart Multiple | B66: =J98 -> 41.36324 | C66: =E51 -> 29876.355 | D66: =C66*B66 -> 1235782.8 | F66: DMart represents the closest listed Indian retail comparable; however, its FY27E EV/EBITDA multiple is materially above the broader peer distribution.
A67: Peer Median | B67: =C108 -> 9.0907389 | C67: =E51 -> 29876.355 | D67: =C67*B67 -> 271598.14 | F67: A normalized multiple is therefore applied to Reliance Retail to avoid transferring the full premium associated with DMart's distinct growth profile, store economics
A68: 75th Percentile | B68: =C110 -> 19.803091 | C68: =E51 -> 29876.355 | D68: =C68*B68 -> 591644.16 | F68: and pure-play positioning.associated with DMart's distinct growth profile | G68: store economics and pure-play positioning.
A69: Selected Retail Multiple | B69: =B60 -> 20.07 | C69: =E51 -> 29876.355 | D69: =C69*B69 -> 599618.44
A72: JIO COMPARABILITY ANALYSIS
A73: Metric | B73: Jio FY27E | C73: Bharti Airtel FY27E | D73: Relative Assessment
A74: Revenue Growth | B74: ='08_Three_Statement_Projections'!D9/'08_Three_Statement_Projections'!C9-1 -> 0.12578927 | C74: 0.1452 | D74: Airtel Higher
A75: EBITDA Margin | B75: =-('08_Three_Statement_Projections'!C18/'08_Three_Statement_Projections'!C9-1) -> 0.5034 | C75: =F97/E97 -> 0.60230705 | D75: Airtel Higher
A76: EV/EBITDA | B76: =C76*0.97 -> 9.3474793 | C76: =J97 -> 9.6365766 | D76: Jio at a ~3% discount
A79: O2C COMPARABILITY ANALYSIS
A80: Metric | B80: O2C FY27E | C80: Indian Oil FY27E | D80: Relative Assessment
A81: Revenue Growth | B81: ='08_Three_Statement_Projections'!D8/'08_Three_Statement_Projections'!C8-1 -> 0.035435396 | C81: =E99/901452.7-1 -> 0.028839339 | D81: Reliance slightly stronger
A82: EBITDA Margin | B82: ='08_Three_Statement_Projections'!C17/'08_Three_Statement_Projections'!C8 -> 0.096995115 | C82: =F99/E99 -> 0.093913419 | D82: Broadly equivalent
A83: EV/EBITDA | B83: 6.5 | C83: =J99 -> 3.6460721
A86: Oil & Gas COMPARABILITY ANALYSIS
A87: Metric | B87: Oil & Gas FY27E | C87: ONGC FY27E | D87: Relative Assessment | F87: Notes
A88: Revenue Growth | B88: ='08_Three_Statement_Projections'!D11/'08_Three_Statement_Projections'!C11-1 -> 0.068962329 | C88: 0.2044 | D88: ONGC stronger
A89: EBITDA Margin | B89: ='08_Three_Statement_Projections'!C20/'08_Three_Statement_Projections'!C11 -> 0.80066759 | C89: =F100/E100 -> 0.26758621 | D89: Reliance materially stronger* | F89: Margin comparison is not strictly like-for-like because Reliance's Oil & Gas segment represents a narrower E&P business scope, while ONGC's reported financials reflect its broader
A90: EV/EBITDA | B90: 5.5 | C90: =J100 -> 2.1260064 | F90: consolidated operations and accounting presentation
A93: COMPARABLE COMPANY TRADING ANALYSIS
A95: Company | B95: Share Price | C95: Market Cap | D95: Enterprise Value | E95: Revenue FY27E | F95: EBITDA FY27E | G95: EPS FY27E | H95: Book Value/Share | I95: EV/Sales FY27E | J95: EV/EBITDA FY27E | K95: P/E FY27E | L95: P/B FY27E | O95: Notes
A96: Reliance Industries | B96: ='13_Executive_Summary'!B9 -> 1310 | C96: ='15_DCF_Sensitivity_Analysis'!C25*B96 -> 1772757.5 | D96: =C96+'08_Three_Statement_Projections'!C79+'08_Three_Statement_Projections'!C88-'08_Three_Statement_Projections'!C62 -> 1965482 | E96: ='08_Three_Statement_Projections'!C14 -> 1267585.9 | F96: ='08_Three_Statement_Projections'!C23 -> 230018.11 | G96: ='14_Key_Metrics_Dashboard'!C9/'15_DCF_Sensitivity_Analysis'!C25 -> 72.692544 | H96: =668.5+0.1*668.5 -> 735.35 | I96: =D96/E96 -> 1.5505711 | J96: =D96/F96 -> 8.5449013 | K96: =B96/G96 -> 18.021106 | L96: =B96/H96 -> 1.7814646
A97: Bharti Airtel | B97: 1906.2 | C97: =B97*624.2 -> 1189850 | D97: =C97+212480 -> 1402330 | E97: 241607 | F97: =121268*1.2 -> 145521.6 | G97: =45.99*1.2 -> 55.188 | H97: =282+0.1*282 -> 310.2 | I97: =D97/E97 -> 5.804178 | J97: =D97/F97 -> 9.6365766 | K97: =B97/G97 -> 34.540117 | L97: =B97/H97 -> 6.1450677 | O97: Peer valuation based on FY27E broker/consensus estimates available around the valuation date. Market prices reflect 7 August 2026. Forecast estimates are sourced from publicly available institutional research reports; estimates may differ across research providers.
A98: Avenue Supermarts | B98: 4045.5 | C98: =B98*65.02 -> 263038.41 | D98: =C98-2450 -> 260588.41 | E98: 82300 | F98: 6300 | G98: =45.62*1.2 -> 54.744 | H98: =375+0.1*375 -> 412.5 | I98: =D98/E98 -> 3.1663233 | J98: =D98/F98 -> 41.36324 | K98: =B98/G98 -> 73.898509 | L98: =B98/H98 -> 9.8072727 | O98: Peer valuation based on FY27E broker/consensus estimates available around the valuation date. Market prices reflect 7 August 2026. Forecast estimates are sourced from publicly available institutional research reports; estimates may differ across research providers.
A99: Indian Oil | B99: 140.5 | C99: =B99*1376.96 -> 193462.88 | D99: =C99+124110 -> 317572.88 | E99: 927450 | F99: 87100 | G99: =28.77*1.1 -> 31.647 | H99: =155.7+0.1*155.7 -> 171.27 | I99: =D99/E99 -> 0.3424151 | J99: =D99/F99 -> 3.6460721 | K99: =B99/G99 -> 4.4395993 | L99: =B99/H99 -> 0.82034215 | O99: Peer valuation based on FY27E broker/consensus estimates available around the valuation date. Market prices reflect 7 August 2026. Forecast estimates are sourced from publicly available institutional research reports; estimates may differ across research providers.
A100: ONGC | B100: 240.09 | C100: =B100*1258.3 -> 302105.25 | D100: =C100+110340 -> 412445.25 | E100: 725000 | F100: 194000 | G100: =32.93*1.2 -> 39.516 | H100: =295.5+0.1*295.5 -> 325.05 | I100: =D100/E100 -> 0.56889 | J100: =D100/F100 -> 2.1260064 | K100: =B100/G100 -> 6.0757668 | L100: =B100/H100 -> 0.73862483 | O100: Peer valuation based on FY27E broker/consensus estimates available around the valuation date. Market prices reflect 7 August 2026. Forecast estimates are sourced from publicly available institutional research reports; estimates may differ across research providers.
A101: Adani Enterprises | B101: 2950.1 | C101: =B101*129.07 -> 380769.41 | D101: =C101+48490 -> 429259.41 | E101: 130136 | F101: 18509 | G101: =55.51*1.2 -> 66.612 | H101: =627+0.1*627 -> 689.7 | I101: =D101/E101 -> 3.2985447 | J101: =D101/F101 -> 23.191929 | K101: =B101/G101 -> 44.287816 | L101: =B101/H101 -> 4.277367 | O101: Peer valuation based on FY27E broker/consensus estimates available around the valuation date. Market prices reflect 7 August 2026. Forecast estimates are sourced from publicly available institutional research reports; estimates may differ across research providers.
A104: SUMMARY STATISTICS
A106: Metric | B106: EV/Sales | C106: EV/EBITDA | D106: P/E | E106: P/B
A107: Mean | B107: =AVERAGE(I96:I101) -> 2.4551537 | C107: =AVERAGE(J96:J101) -> 14.751454 | D107: =AVERAGE(K96:K101) -> 30.210486 | E107: =AVERAGE(L96:L101) -> 3.9283565
A108: Median | B108: =MEDIAN(I96:I101) -> 2.3584472 | C108: =MEDIAN(J96:J101) -> 9.0907389 | D108: =MEDIAN(K96:K101) -> 26.280611 | E108: =MEDIAN(L96:L101) -> 3.0294158
A109: 25th Percentile | B109: =_xlfn.PERCENTILE.INC(I96:I101,25%) -> 0.81431026 | C109: =_xlfn.PERCENTILE.INC(J96:J101,25%) -> 4.8707794 | D109: =_xlfn.PERCENTILE.INC(K96:K101,25%) -> 9.0621015 | E109: =_xlfn.PERCENTILE.INC(L96:L101,25%) -> 1.0606228
A110: 75th Percentile | B110: =_xlfn.PERCENTILE.INC(I96:I101,75%) -> 3.2654893 | C110: =_xlfn.PERCENTILE.INC(J96:J101,75%) -> 19.803091 | D110: =_xlfn.PERCENTILE.INC(K96:K101,75%) -> 41.850891 | E110: =_xlfn.PERCENTILE.INC(L96:L101,75%) -> 5.6781425
A111: Minimum | B111: =MIN(I96:I101) -> 0.3424151 | C111: =MIN(J96:J101) -> 2.1260064 | D111: =MIN(K96:K101) -> 4.4395993 | E111: =MIN(L96:L101) -> 0.73862483
A112: Maximum | B112: =MAX((I96:I101)) -> 5.804178 | C112: =MAX((J96:J101)) -> 41.36324 | D112: =MAX((K96:K101)) -> 73.898509 | E112: =MAX((L96:L101)) -> 9.8072727
A113: Standard Deviation | B113: =STDEV(I96:I101) -> 2.0626662 | C113: =STDEV(J96:J101) -> 15.012285 | D113: =STDEV(K96:K101) -> 26.53588 | E113: =STDEV(L96:L101) -> 3.5788422
A117: RELIANCE PREMIUM/DISCOUNT
A119: Metric | C119: Reliance | D119: Peer Median | E119: Premium / Discount | F119: Implied Equity Value | G119: Target Price
A120: EV/Sales | C120: =I96 -> 1.5505711 | D120: =B108 -> 2.3584472 | E120: =C120/D120-1 -> -0.34254578 | F120: =D120*E96+'15_DCF_Sensitivity_Analysis'!C21-'15_DCF_Sensitivity_Analysis'!C22 -> 2796809.9 | G120: =F120/'15_DCF_Sensitivity_Analysis'!C25 -> 2066.7356
A121: EV/EBITDA | C121: =J96 -> 8.5449013 | D121: =C108 -> 9.0907389 | E121: =C121/D121-1 -> -0.060043263 | F121: =D121*F96+'15_DCF_Sensitivity_Analysis'!C21-'15_DCF_Sensitivity_Analysis'!C22 -> 1898310 | G121: =F121/'15_DCF_Sensitivity_Analysis'!C25 -> 1402.7785
A122: P/E | C122: =K96 -> 18.021106 | D122: =D108 -> 26.280611 | E122: =C122/D122-1 -> -0.31428135 | F122: - | G122: =D122*G96 -> 1910.4045
A123: P/B | C123: =L96 -> 1.7814646 | D123: =E108 -> 3.0294158 | E123: =C123/D123-1 -> -0.4119445 | F123: - | G123: =D123*H96 -> 2227.6809
A126: COMPARABLE VALUE SUMMARY
A127: Method | B127: Weight | C127: Target Price | D127: Weighted Target Price
A128: EV/Sales Target | B128: 0.13 | C128: =G120 -> 2066.7356 | D128: =C128*B128 -> 268.67562
A129: EV/EBITDA Target | B129: 0.45 | C129: =G121 -> 1402.7785 | D129: =C129*B129 -> 631.25034
A130: P/E Target | B130: 0.35 | C130: =G122 -> 1910.4045 | D130: =C130*B130 -> 668.64157
A131: P/B Target | B131: 0.07 | C131: =G123 -> 2227.6809 | D131: =C131*B131 -> 155.93766
A133: Comparable Target Price | D133: =SUM(D128:D131) -> 1724.5052
A136: CONSOLIDATED COMPS TARGET PRICE
A137: Metric | B137: Value
A138: ='13_Executive_Summary'!A9 -> Current NSE Market Price (As of Aug 12, 2026) | B138: ='13_Executive_Summary'!B9 -> 1310
A139: Comparable Target Price | B139: =D133 -> 1724.5052
A140: Implied Upside / (Downside) | B140: =B139/B138-1 -> 0.31641618
...

Sheet 17_Final_Valuation_Dashboard
B1: FINAL VALUATION DASHBOARD
B3: PRIMARY SCENERIO VALUATION
B4: Scenerio | C4: Implied Share Price
B5: Bear | C5: ='12_Scenario_Analysis_Dashboard'!D12 -> 952.168
B6: Base | C6: ='12_Scenario_Analysis_Dashboard'!C12 -> 1386.716
B7: Bull | C7: ='12_Scenario_Analysis_Dashboard'!B12 -> 1854.682
B8: Current NSE Price | C8: ='12_Scenario_Analysis_Dashboard'!B13 -> 1310
B9: Base Upside | C9: =C6/C8-1 -> 0.058561832
B12: INDEPENDENT VALUATION CROSS CHECK
B13: Scenerio | C13: Implied Share Price
B14: Relative CCA | C14: ='16_Relative_Valuation'!E198 -> 1724.5052
B15: Market SOTP | C15: ='16_Relative_Valuation'!E199 -> 1219.0916
B16: DCF Perpetuity | C16: ='16_Relative_Valuation'!E200 -> 1219.0684
B17: DCF Segment Exit | C17: ='16_Relative_Valuation'!E201 -> 1454.3686
B19: Minimum | C19: =MIN(C14:C17) -> 1219.0684
B20: Median | C20: =MEDIAN(C14:C17) -> 1336.7301
B21: Maximum | C21: =MAX(C14:C17) -> 1724.5052
B24: OBSERVABLE PEER ANCHORS
B25: Segment | C25: Observable Peer Anchor | D25: Main Model | E25: Rationale
B26: Jio | C26: 9.57x | D26: 15.0x | E26: Growth / digital ecosystem premium
B27: Retail | C27: 20.07x | D27: 22.0x | E27: Modest premium vs normalized peer
B28: O2C | C28: 3.68x | D28: 6.5x | E28: Private-sector / integration / asset-quality premium
B29: Oil & Gas | C29: 2.11x | D29: 5.5x | E29: Private-sector / asset-quality / portfolio premium
